{
  "metadata": {
    "created": "2025-10-23T15:49:03.021959",
    "device_ip": "192.168.100.100:80",
    "max_hours": 3.0,
    "description": "Rolling history of Memmert incubator data",
    "last_updated": "2025-10-30T01:23:36.057293",
    "total_entries": 157,
    "time_span_hours": 2.99
  },
  "data": [
    {
      "timestamp": "2025-10-29T22:24:12.462808",
      "mode": "Timer",
      "readings": {
        "Temp1Read": 24.763,
        "HumRead": 55.643,
        "CO2Read": null,
        "O2Read": null,
        "FanRead": null
      },
      "setpoints": {
        "TempSet": 24.1,
        "HumSet": 55.3,
        "CO2Set": null,
        "O2Set": null,
        "FanSet": null
      }
    },
    {
      "timestamp": "2025-10-29T22:25:21.288617",
      "mode": "Timer",
      "readings": {
        "Temp1Read": 24.768,
        "HumRead": 55.521,
        "CO2Read": null,
        "O2Read": null,
        "FanRead": null
      },
      "setpoints": {
        "TempSet": 24.1,
        "HumSet": 55.3,
        "CO2Set": null,
        "O2Set": null,
        "FanSet": null
      }
    },
    {
      "timestamp": "2025-10-29T22:26:31.054635",
      "mode": "Timer",
      "readings": {
        "Temp1Read": 24.758,
        "HumRead": 55.644,
        "CO2Read": null,
        "O2Read": null,
        "FanRead": null
      },
      "setpoints": {
        "TempSet": 24.1,
        "HumSet": 55.3,
        "CO2Set": null,
        "O2Set": null,
        "FanSet": null
      }
    },
    {
      "timestamp": "2025-10-29T22:27:41.110636",
      "mode": "Timer",
      "readings": {
        "Temp1Read": 24.737,
        "HumRead": 55.675,
        "CO2Read": null,
        "O2Read": null,
        "FanRead": null
      },
      "setpoints": {
        "TempSet": 24.1,
        "HumSet": 55.3,
        "CO2Set": null,
        "O2Set": null,
        "FanSet": null
      }
    },
    {
      "timestamp": "2025-10-29T22:28:50.067965",
      "mode": "Timer",
      "readings": {
        "Temp1Read": 24.724,
        "HumRead": 55.49,
        "CO2Read": null,
        "O2Read": null,
        "FanRead": null
      },
      "setpoints": {
        "TempSet": 24.1,
        "HumSet": 55.3,
        "CO2Set": null,
        "O2Set": null,
        "FanSet": null
      }
    },
    {
      "timestamp": "2025-10-29T22:30:00.149349",
      "mode": "Timer",
      "readings": {
        "Temp1Read": 24.713,
        "HumRead": 55.582,
        "CO2Read": null,
        "O2Read": null,
        "FanRead": null
      },
      "setpoints": {
        "TempSet": 24.1,
        "HumSet": 55.3,
        "CO2Set": null,
        "O2Set": null,
        "FanSet": null
      }
    },
    {
      "timestamp": "2025-10-29T22:31:09.190317",
      "mode": "Timer",
      "readings": {
        "Temp1Read": 24.691,
        "HumRead": 55.705,
        "CO2Read": null,
        "O2Read": null,
        "FanRead": null
      },
      "setpoints": {
        "TempSet": 24.1,
        "HumSet": 55.3,
        "CO2Set": null,
        "O2Set": null,
        "FanSet": null
      }
    },
    {
      "timestamp": "2025-10-29T22:32:17.970498",
      "mode": "Timer",
      "readings": {
        "Temp1Read": 24.681,
        "HumRead": 55.582,
        "CO2Read": null,
        "O2Read": null,
        "FanRead": null
      },
      "setpoints": {
        "TempSet": 24.1,
        "HumSet": 55.3,
        "CO2Set": null,
        "O2Set": null,
        "FanSet": null
      }
    },
    {
      "timestamp": "2025-10-29T22:33:27.563287",
      "mode": "Timer",
      "readings": {
        "Temp1Read": 24.676,
        "HumRead": 55.52,
        "CO2Read": null,
        "O2Read": null,
        "FanRead": null
      },
      "setpoints": {
        "TempSet": 24.1,
        "HumSet": 55.3,
        "CO2Set": null,
        "O2Set": null,
        "FanSet": null
      }
    },
    {
      "timestamp": "2025-10-29T22:34:35.713918",
      "mode": "Timer",
      "readings": {
        "Temp1Read": 24.649,
        "HumRead": 55.704,
        "CO2Read": null,
        "O2Read": null,
        "FanRead": null
      },
      "setpoints": {
        "TempSet": 24.1,
        "HumSet": 55.3,
        "CO2Set": null,
        "O2Set": null,
        "FanSet": null
      }
    },
    {
      "timestamp": "2025-10-29T22:35:44.270086",
      "mode": "Timer",
      "readings": {
        "Temp1Read": 24.634,
        "HumRead": 55.644,
        "CO2Read": null,
        "O2Read": null,
        "FanRead": null
      },
      "setpoints": {
        "TempSet": 24.1,
        "HumSet": 55.3,
        "CO2Set": null,
        "O2Set": null,
        "FanSet": null
      }
    },
    {
      "timestamp": "2025-10-29T22:36:54.100169",
      "mode": "Timer",
      "readings": {
        "Temp1Read": 24.626,
        "HumRead": 55.644,
        "CO2Read": null,
        "O2Read": null,
        "FanRead": null
      },
      "setpoints": {
        "TempSet": 24.1,
        "HumSet": 55.3,
        "CO2Set": null,
        "O2Set": null,
        "FanSet": null
      }
    },
    {
      "timestamp": "2025-10-29T22:38:04.540438",
      "mode": "Timer",
      "readings": {
        "Temp1Read": 24.605,
        "HumRead": 55.614,
        "CO2Read": null,
        "O2Read": null,
        "FanRead": null
      },
      "setpoints": {
        "TempSet": 24.1,
        "HumSet": 55.3,
        "CO2Set": null,
        "O2Set": null,
        "FanSet": null
      }
    },
    {
      "timestamp": "2025-10-29T22:39:14.347369",
      "mode": "Timer",
      "readings": {
        "Temp1Read": 24.601,
        "HumRead": 55.644,
        "CO2Read": null,
        "O2Read": null,
        "FanRead": null
      },
      "setpoints": {
        "TempSet": 24.1,
        "HumSet": 55.3,
        "CO2Set": null,
        "O2Set": null,
        "FanSet": null
      }
    },
    {
      "timestamp": "2025-10-29T22:40:22.427230",
      "mode": "Timer",
      "readings": {
        "Temp1Read": 24.587,
        "HumRead": 55.705,
        "CO2Read": null,
        "O2Read": null,
        "FanRead": null
      },
      "setpoints": {
        "TempSet": 24.1,
        "HumSet": 55.3,
        "CO2Set": null,
        "O2Set": null,
        "FanSet": null
      }
    },
    {
      "timestamp": "2025-10-29T22:41:30.738839",
      "mode": "Timer",
      "readings": {
        "Temp1Read": 24.562,
        "HumRead": 55.613,
        "CO2Read": null,
        "O2Read": null,
        "FanRead": null
      },
      "setpoints": {
        "TempSet": 24.1,
        "HumSet": 55.3,
        "CO2Set": null,
        "O2Set": null,
        "FanSet": null
      }
    },
    {
      "timestamp": "2025-10-29T22:42:40.560714",
      "mode": "Timer",
      "readings": {
        "Temp1Read": 24.564,
        "HumRead": 55.582,
        "CO2Read": null,
        "O2Read": null,
        "FanRead": null
      },
      "setpoints": {
        "TempSet": 24.1,
        "HumSet": 55.3,
        "CO2Set": null,
        "O2Set": null,
        "FanSet": null
      }
    },
    {
      "timestamp": "2025-10-29T22:43:48.832233",
      "mode": "Timer",
      "readings": {
        "Temp1Read": 24.547,
        "HumRead": 55.643,
        "CO2Read": null,
        "O2Read": null,
        "FanRead": null
      },
      "setpoints": {
        "TempSet": 24.1,
        "HumSet": 55.3,
        "CO2Set": null,
        "O2Set": null,
        "FanSet": null
      }
    },
    {
      "timestamp": "2025-10-29T22:44:56.928993",
      "mode": "Timer",
      "readings": {
        "Temp1Read": 24.542,
        "HumRead": 55.643,
        "CO2Read": null,
        "O2Read": null,
        "FanRead": null
      },
      "setpoints": {
        "TempSet": 24.1,
        "HumSet": 55.3,
        "CO2Set": null,
        "O2Set": null,
        "FanSet": null
      }
    },
    {
      "timestamp": "2025-10-29T22:46:05.127902",
      "mode": "Timer",
      "readings": {
        "Temp1Read": 24.52,
        "HumRead": 55.583,
        "CO2Read": null,
        "O2Read": null,
        "FanRead": null
      },
      "setpoints": {
        "TempSet": 24.1,
        "HumSet": 55.3,
        "CO2Set": null,
        "O2Set": null,
        "FanSet": null
      }
    },
    {
      "timestamp": "2025-10-29T22:47:15.849850",
      "mode": "Timer",
      "readings": {
        "Temp1Read": 24.514,
        "HumRead": 55.613,
        "CO2Read": null,
        "O2Read": null,
        "FanRead": null
      },
      "setpoints": {
        "TempSet": 24.1,
        "HumSet": 55.3,
        "CO2Set": null,
        "O2Set": null,
        "FanSet": null
      }
    },
    {
      "timestamp": "2025-10-29T22:48:24.610355",
      "mode": "Timer",
      "readings": {
        "Temp1Read": 24.5,
        "HumRead": 55.705,
        "CO2Read": null,
        "O2Read": null,
        "FanRead": null
      },
      "setpoints": {
        "TempSet": 24.1,
        "HumSet": 55.3,
        "CO2Set": null,
        "O2Set": null,
        "FanSet": null
      }
    },
    {
      "timestamp": "2025-10-29T22:49:32.372293",
      "mode": "Timer",
      "readings": {
        "Temp1Read": 24.482,
        "HumRead": 55.582,
        "CO2Read": null,
        "O2Read": null,
        "FanRead": null
      },
      "setpoints": {
        "TempSet": 24.1,
        "HumSet": 55.3,
        "CO2Set": null,
        "O2Set": null,
        "FanSet": null
      }
    },
    {
      "timestamp": "2025-10-29T22:50:42.074064",
      "mode": "Timer",
      "readings": {
        "Temp1Read": 24.46,
        "HumRead": 55.736,
        "CO2Read": null,
        "O2Read": null,
        "FanRead": null
      },
      "setpoints": {
        "TempSet": 24.1,
        "HumSet": 55.3,
        "CO2Set": null,
        "O2Set": null,
        "FanSet": null
      }
    },
    {
      "timestamp": "2025-10-29T22:51:50.938771",
      "mode": "Timer",
      "readings": {
        "Temp1Read": 24.464,
        "HumRead": 55.459,
        "CO2Read": null,
        "O2Read": null,
        "FanRead": null
      },
      "setpoints": {
        "TempSet": 24.1,
        "HumSet": 55.3,
        "CO2Set": null,
        "O2Set": null,
        "FanSet": null
      }
    },
    {
      "timestamp": "2025-10-29T22:53:01.760258",
      "mode": "Timer",
      "readings": {
        "Temp1Read": 24.44,
        "HumRead": 55.645,
        "CO2Read": null,
        "O2Read": null,
        "FanRead": null
      },
      "setpoints": {
        "TempSet": 24.1,
        "HumSet": 55.3,
        "CO2Set": null,
        "O2Set": null,
        "FanSet": null
      }
    },
    {
      "timestamp": "2025-10-29T22:54:10.646686",
      "mode": "Timer",
      "readings": {
        "Temp1Read": 24.427,
        "HumRead": 55.582,
        "CO2Read": null,
        "O2Read": null,
        "FanRead": null
      },
      "setpoints": {
        "TempSet": 24.1,
        "HumSet": 55.3,
        "CO2Set": null,
        "O2Set": null,
        "FanSet": null
      }
    },
    {
      "timestamp": "2025-10-29T22:55:19.601915",
      "mode": "Timer",
      "readings": {
        "Temp1Read": 24.416,
        "HumRead": 55.612,
        "CO2Read": null,
        "O2Read": null,
        "FanRead": null
      },
      "setpoints": {
        "TempSet": 24.1,
        "HumSet": 55.3,
        "CO2Set": null,
        "O2Set": null,
        "FanSet": null
      }
    },
    {
      "timestamp": "2025-10-29T22:56:29.564506",
      "mode": "Timer",
      "readings": {
        "Temp1Read": 24.407,
        "HumRead": 55.645,
        "CO2Read": null,
        "O2Read": null,
        "FanRead": null
      },
      "setpoints": {
        "TempSet": 24.1,
        "HumSet": 55.3,
        "CO2Set": null,
        "O2Set": null,
        "FanSet": null
      }
    },
    {
      "timestamp": "2025-10-29T22:57:38.686227",
      "mode": "Timer",
      "readings": {
        "Temp1Read": 24.393,
        "HumRead": 55.583,
        "CO2Read": null,
        "O2Read": null,
        "FanRead": null
      },
      "setpoints": {
        "TempSet": 24.1,
        "HumSet": 55.3,
        "CO2Set": null,
        "O2Set": null,
        "FanSet": null
      }
    },
    {
      "timestamp": "2025-10-29T22:58:48.615701",
      "mode": "Timer",
      "readings": {
        "Temp1Read": 24.385,
        "HumRead": 55.583,
        "CO2Read": null,
        "O2Read": null,
        "FanRead": null
      },
      "setpoints": {
        "TempSet": 24.1,
        "HumSet": 55.3,
        "CO2Set": null,
        "O2Set": null,
        "FanSet": null
      }
    },
    {
      "timestamp": "2025-10-29T22:59:57.624534",
      "mode": "Timer",
      "readings": {
        "Temp1Read": 24.371,
        "HumRead": 55.551,
        "CO2Read": null,
        "O2Read": null,
        "FanRead": null
      },
      "setpoints": {
        "TempSet": 24.1,
        "HumSet": 55.3,
        "CO2Set": null,
        "O2Set": null,
        "FanSet": null
      }
    },
    {
      "timestamp": "2025-10-29T23:01:09.765139",
      "mode": "Timer",
      "readings": {
        "Temp1Read": 24.351,
        "HumRead": 55.551,
        "CO2Read": null,
        "O2Read": null,
        "FanRead": null
      },
      "setpoints": {
        "TempSet": 24.1,
        "HumSet": 55.3,
        "CO2Set": null,
        "O2Set": null,
        "FanSet": null
      }
    },
    {
      "timestamp": "2025-10-29T23:02:20.415769",
      "mode": "Timer",
      "readings": {
        "Temp1Read": 24.34,
        "HumRead": 55.612,
        "CO2Read": null,
        "O2Read": null,
        "FanRead": null
      },
      "setpoints": {
        "TempSet": 24.1,
        "HumSet": 55.3,
        "CO2Set": null,
        "O2Set": null,
        "FanSet": null
      }
    },
    {
      "timestamp": "2025-10-29T23:03:28.709030",
      "mode": "Timer",
      "readings": {
        "Temp1Read": 24.334,
        "HumRead": 55.644,
        "CO2Read": null,
        "O2Read": null,
        "FanRead": null
      },
      "setpoints": {
        "TempSet": 24.1,
        "HumSet": 55.3,
        "CO2Set": null,
        "O2Set": null,
        "FanSet": null
      }
    },
    {
      "timestamp": "2025-10-29T23:04:37.641167",
      "mode": "Timer",
      "readings": {
        "Temp1Read": 24.313,
        "HumRead": 55.645,
        "CO2Read": null,
        "O2Read": null,
        "FanRead": null
      },
      "setpoints": {
        "TempSet": 24.1,
        "HumSet": 55.3,
        "CO2Set": null,
        "O2Set": null,
        "FanSet": null
      }
    },
    {
      "timestamp": "2025-10-29T23:05:45.738795",
      "mode": "Timer",
      "readings": {
        "Temp1Read": 24.317,
        "HumRead": 55.676,
        "CO2Read": null,
        "O2Read": null,
        "FanRead": null
      },
      "setpoints": {
        "TempSet": 24.1,
        "HumSet": 55.3,
        "CO2Set": null,
        "O2Set": null,
        "FanSet": null
      }
    },
    {
      "timestamp": "2025-10-29T23:06:55.492128",
      "mode": "Timer",
      "readings": {
        "Temp1Read": 24.297,
        "HumRead": 55.604,
        "CO2Read": null,
        "O2Read": null,
        "FanRead": null
      },
      "setpoints": {
        "TempSet": 24.1,
        "HumSet": 55.3,
        "CO2Set": null,
        "O2Set": null,
        "FanSet": null
      }
    },
    {
      "timestamp": "2025-10-29T23:08:05.318502",
      "mode": "Timer",
      "readings": {
        "Temp1Read": 24.292,
        "HumRead": 55.635,
        "CO2Read": null,
        "O2Read": null,
        "FanRead": null
      },
      "setpoints": {
        "TempSet": 24.1,
        "HumSet": 55.3,
        "CO2Set": null,
        "O2Set": null,
        "FanSet": null
      }
    },
    {
      "timestamp": "2025-10-29T23:09:13.475120",
      "mode": "Timer",
      "readings": {
        "Temp1Read": 24.266,
        "HumRead": 55.634,
        "CO2Read": null,
        "O2Read": null,
        "FanRead": null
      },
      "setpoints": {
        "TempSet": 24.1,
        "HumSet": 55.3,
        "CO2Set": null,
        "O2Set": null,
        "FanSet": null
      }
    },
    {
      "timestamp": "2025-10-29T23:10:22.658820",
      "mode": "Timer",
      "readings": {
        "Temp1Read": 24.27,
        "HumRead": 55.511,
        "CO2Read": null,
        "O2Read": null,
        "FanRead": null
      },
      "setpoints": {
        "TempSet": 24.1,
        "HumSet": 55.3,
        "CO2Set": null,
        "O2Set": null,
        "FanSet": null
      }
    },
    {
      "timestamp": "2025-10-29T23:11:31.600953",
      "mode": "Timer",
      "readings": {
        "Temp1Read": 24.264,
        "HumRead": 55.697,
        "CO2Read": null,
        "O2Read": null,
        "FanRead": null
      },
      "setpoints": {
        "TempSet": 24.1,
        "HumSet": 55.3,
        "CO2Set": null,
        "O2Set": null,
        "FanSet": null
      }
    },
    {
      "timestamp": "2025-10-29T23:12:40.397745",
      "mode": "Timer",
      "readings": {
        "Temp1Read": 24.246,
        "HumRead": 55.542,
        "CO2Read": null,
        "O2Read": null,
        "FanRead": null
      },
      "setpoints": {
        "TempSet": 24.1,
        "HumSet": 55.3,
        "CO2Set": null,
        "O2Set": null,
        "FanSet": null
      }
    },
    {
      "timestamp": "2025-10-29T23:13:50.283627",
      "mode": "Timer",
      "readings": {
        "Temp1Read": 24.225,
        "HumRead": 55.541,
        "CO2Read": null,
        "O2Read": null,
        "FanRead": null
      },
      "setpoints": {
        "TempSet": 24.1,
        "HumSet": 55.3,
        "CO2Set": null,
        "O2Set": null,
        "FanSet": null
      }
    },
    {
      "timestamp": "2025-10-29T23:14:59.344007",
      "mode": "Timer",
      "readings": {
        "Temp1Read": 24.217,
        "HumRead": 55.635,
        "CO2Read": null,
        "O2Read": null,
        "FanRead": null
      },
      "setpoints": {
        "TempSet": 24.1,
        "HumSet": 55.3,
        "CO2Set": null,
        "O2Set": null,
        "FanSet": null
      }
    },
    {
      "timestamp": "2025-10-29T23:16:08.486333",
      "mode": "Timer",
      "readings": {
        "Temp1Read": 24.21,
        "HumRead": 55.727,
        "CO2Read": null,
        "O2Read": null,
        "FanRead": null
      },
      "setpoints": {
        "TempSet": 24.1,
        "HumSet": 55.3,
        "CO2Set": null,
        "O2Set": null,
        "FanSet": null
      }
    },
    {
      "timestamp": "2025-10-29T23:17:16.653013",
      "mode": "Timer",
      "readings": {
        "Temp1Read": 24.203,
        "HumRead": 55.511,
        "CO2Read": null,
        "O2Read": null,
        "FanRead": null
      },
      "setpoints": {
        "TempSet": 24.1,
        "HumSet": 55.3,
        "CO2Set": null,
        "O2Set": null,
        "FanSet": null
      }
    },
    {
      "timestamp": "2025-10-29T23:18:25.552283",
      "mode": "Timer",
      "readings": {
        "Temp1Read": 24.19,
        "HumRead": 55.573,
        "CO2Read": null,
        "O2Read": null,
        "FanRead": null
      },
      "setpoints": {
        "TempSet": 24.1,
        "HumSet": 55.3,
        "CO2Set": null,
        "O2Set": null,
        "FanSet": null
      }
    },
    {
      "timestamp": "2025-10-29T23:19:34.380716",
      "mode": "Timer",
      "readings": {
        "Temp1Read": 24.173,
        "HumRead": 55.573,
        "CO2Read": null,
        "O2Read": null,
        "FanRead": null
      },
      "setpoints": {
        "TempSet": 24.1,
        "HumSet": 55.3,
        "CO2Set": null,
        "O2Set": null,
        "FanSet": null
      }
    },
    {
      "timestamp": "2025-10-29T23:20:44.929671",
      "mode": "Timer",
      "readings": {
        "Temp1Read": 24.177,
        "HumRead": 55.542,
        "CO2Read": null,
        "O2Read": null,
        "FanRead": null
      },
      "setpoints": {
        "TempSet": 24.1,
        "HumSet": 55.3,
        "CO2Set": null,
        "O2Set": null,
        "FanSet": null
      }
    },
    {
      "timestamp": "2025-10-29T23:21:55.507803",
      "mode": "Timer",
      "readings": {
        "Temp1Read": 24.163,
        "HumRead": 55.48,
        "CO2Read": null,
        "O2Read": null,
        "FanRead": null
      },
      "setpoints": {
        "TempSet": 24.1,
        "HumSet": 55.3,
        "CO2Set": null,
        "O2Set": null,
        "FanSet": null
      }
    },
    {
      "timestamp": "2025-10-29T23:23:04.424074",
      "mode": "Timer",
      "readings": {
        "Temp1Read": 24.157,
        "HumRead": 55.665,
        "CO2Read": null,
        "O2Read": null,
        "FanRead": null
      },
      "setpoints": {
        "TempSet": 24.1,
        "HumSet": 55.3,
        "CO2Set": null,
        "O2Set": null,
        "FanSet": null
      }
    },
    {
      "timestamp": "2025-10-29T23:24:14.270339",
      "mode": "Timer",
      "readings": {
        "Temp1Read": 24.135,
        "HumRead": 55.573,
        "CO2Read": null,
        "O2Read": null,
        "FanRead": null
      },
      "setpoints": {
        "TempSet": 24.1,
        "HumSet": 55.3,
        "CO2Set": null,
        "O2Set": null,
        "FanSet": null
      }
    },
    {
      "timestamp": "2025-10-29T23:25:23.221855",
      "mode": "Timer",
      "readings": {
        "Temp1Read": 24.11,
        "HumRead": 55.542,
        "CO2Read": null,
        "O2Read": null,
        "FanRead": null
      },
      "setpoints": {
        "TempSet": 24.1,
        "HumSet": 55.3,
        "CO2Set": null,
        "O2Set": null,
        "FanSet": null
      }
    },
    {
      "timestamp": "2025-10-29T23:26:31.381239",
      "mode": "Timer",
      "readings": {
        "Temp1Read": 24.103,
        "HumRead": 55.604,
        "CO2Read": null,
        "O2Read": null,
        "FanRead": null
      },
      "setpoints": {
        "TempSet": 24.1,
        "HumSet": 55.3,
        "CO2Set": null,
        "O2Set": null,
        "FanSet": null
      }
    },
    {
      "timestamp": "2025-10-29T23:27:40.477387",
      "mode": "Timer",
      "readings": {
        "Temp1Read": 24.103,
        "HumRead": 55.542,
        "CO2Read": null,
        "O2Read": null,
        "FanRead": null
      },
      "setpoints": {
        "TempSet": 24.1,
        "HumSet": 55.3,
        "CO2Set": null,
        "O2Set": null,
        "FanSet": null
      }
    },
    {
      "timestamp": "2025-10-29T23:28:48.891678",
      "mode": "Timer",
      "readings": {
        "Temp1Read": 24.088,
        "HumRead": 55.634,
        "CO2Read": null,
        "O2Read": null,
        "FanRead": null
      },
      "setpoints": {
        "TempSet": 24.1,
        "HumSet": 55.3,
        "CO2Set": null,
        "O2Set": null,
        "FanSet": null
      }
    },
    {
      "timestamp": "2025-10-29T23:29:57.790147",
      "mode": "Timer",
      "readings": {
        "Temp1Read": 24.075,
        "HumRead": 55.635,
        "CO2Read": null,
        "O2Read": null,
        "FanRead": null
      },
      "setpoints": {
        "TempSet": 24.1,
        "HumSet": 55.3,
        "CO2Set": null,
        "O2Set": null,
        "FanSet": null
      }
    },
    {
      "timestamp": "2025-10-29T23:31:05.866591",
      "mode": "Timer",
      "readings": {
        "Temp1Read": 24.06,
        "HumRead": 55.79,
        "CO2Read": null,
        "O2Read": null,
        "FanRead": null
      },
      "setpoints": {
        "TempSet": 24.1,
        "HumSet": 55.3,
        "CO2Set": null,
        "O2Set": null,
        "FanSet": null
      }
    },
    {
      "timestamp": "2025-10-29T23:32:15.075520",
      "mode": "Timer",
      "readings": {
        "Temp1Read": 24.054,
        "HumRead": 55.603,
        "CO2Read": null,
        "O2Read": null,
        "FanRead": null
      },
      "setpoints": {
        "TempSet": 24.1,
        "HumSet": 55.3,
        "CO2Set": null,
        "O2Set": null,
        "FanSet": null
      }
    },
    {
      "timestamp": "2025-10-29T23:33:23.451221",
      "mode": "Timer",
      "readings": {
        "Temp1Read": 24.048,
        "HumRead": 55.541,
        "CO2Read": null,
        "O2Read": null,
        "FanRead": null
      },
      "setpoints": {
        "TempSet": 24.1,
        "HumSet": 55.3,
        "CO2Set": null,
        "O2Set": null,
        "FanSet": null
      }
    },
    {
      "timestamp": "2025-10-29T23:34:31.584046",
      "mode": "Timer",
      "readings": {
        "Temp1Read": 24.05,
        "HumRead": 55.603,
        "CO2Read": null,
        "O2Read": null,
        "FanRead": null
      },
      "setpoints": {
        "TempSet": 24.1,
        "HumSet": 55.3,
        "CO2Set": null,
        "O2Set": null,
        "FanSet": null
      }
    },
    {
      "timestamp": "2025-10-29T23:35:40.705719",
      "mode": "Timer",
      "readings": {
        "Temp1Read": 24.04,
        "HumRead": 55.572,
        "CO2Read": null,
        "O2Read": null,
        "FanRead": null
      },
      "setpoints": {
        "TempSet": 24.1,
        "HumSet": 55.3,
        "CO2Set": null,
        "O2Set": null,
        "FanSet": null
      }
    },
    {
      "timestamp": "2025-10-29T23:36:49.106520",
      "mode": "Timer",
      "readings": {
        "Temp1Read": 24.043,
        "HumRead": 55.603,
        "CO2Read": null,
        "O2Read": null,
        "FanRead": null
      },
      "setpoints": {
        "TempSet": 24.1,
        "HumSet": 55.3,
        "CO2Set": null,
        "O2Set": null,
        "FanSet": null
      }
    },
    {
      "timestamp": "2025-10-29T23:37:57.289583",
      "mode": "Timer",
      "readings": {
        "Temp1Read": 24.028,
        "HumRead": 55.572,
        "CO2Read": null,
        "O2Read": null,
        "FanRead": null
      },
      "setpoints": {
        "TempSet": 24.1,
        "HumSet": 55.3,
        "CO2Set": null,
        "O2Set": null,
        "FanSet": null
      }
    },
    {
      "timestamp": "2025-10-29T23:39:05.393278",
      "mode": "Timer",
      "readings": {
        "Temp1Read": 24.023,
        "HumRead": 55.541,
        "CO2Read": null,
        "O2Read": null,
        "FanRead": null
      },
      "setpoints": {
        "TempSet": 24.1,
        "HumSet": 55.3,
        "CO2Set": null,
        "O2Set": null,
        "FanSet": null
      }
    },
    {
      "timestamp": "2025-10-29T23:40:14.862096",
      "mode": "Timer",
      "readings": {
        "Temp1Read": 24.028,
        "HumRead": 55.541,
        "CO2Read": null,
        "O2Read": null,
        "FanRead": null
      },
      "setpoints": {
        "TempSet": 24.1,
        "HumSet": 55.3,
        "CO2Set": null,
        "O2Set": null,
        "FanSet": null
      }
    },
    {
      "timestamp": "2025-10-29T23:41:23.068028",
      "mode": "Timer",
      "readings": {
        "Temp1Read": 24.02,
        "HumRead": 55.541,
        "CO2Read": null,
        "O2Read": null,
        "FanRead": null
      },
      "setpoints": {
        "TempSet": 24.1,
        "HumSet": 55.3,
        "CO2Set": null,
        "O2Set": null,
        "FanSet": null
      }
    },
    {
      "timestamp": "2025-10-29T23:42:31.578425",
      "mode": "Timer",
      "readings": {
        "Temp1Read": 24.02,
        "HumRead": 55.448,
        "CO2Read": null,
        "O2Read": null,
        "FanRead": null
      },
      "setpoints": {
        "TempSet": 24.1,
        "HumSet": 55.3,
        "CO2Set": null,
        "O2Set": null,
        "FanSet": null
      }
    },
    {
      "timestamp": "2025-10-29T23:43:40.177909",
      "mode": "Timer",
      "readings": {
        "Temp1Read": 24.034,
        "HumRead": 55.449,
        "CO2Read": null,
        "O2Read": null,
        "FanRead": null
      },
      "setpoints": {
        "TempSet": 24.1,
        "HumSet": 55.3,
        "CO2Set": null,
        "O2Set": null,
        "FanSet": null
      }
    },
    {
      "timestamp": "2025-10-29T23:44:48.727897",
      "mode": "Timer",
      "readings": {
        "Temp1Read": 24.019,
        "HumRead": 55.479,
        "CO2Read": null,
        "O2Read": null,
        "FanRead": null
      },
      "setpoints": {
        "TempSet": 24.1,
        "HumSet": 55.3,
        "CO2Set": null,
        "O2Set": null,
        "FanSet": null
      }
    },
    {
      "timestamp": "2025-10-29T23:45:56.929051",
      "mode": "Timer",
      "readings": {
        "Temp1Read": 24.031,
        "HumRead": 55.573,
        "CO2Read": null,
        "O2Read": null,
        "FanRead": null
      },
      "setpoints": {
        "TempSet": 24.1,
        "HumSet": 55.3,
        "CO2Set": null,
        "O2Set": null,
        "FanSet": null
      }
    },
    {
      "timestamp": "2025-10-29T23:47:05.290167",
      "mode": "Timer",
      "readings": {
        "Temp1Read": 24.015,
        "HumRead": 55.419,
        "CO2Read": null,
        "O2Read": null,
        "FanRead": null
      },
      "setpoints": {
        "TempSet": 24.1,
        "HumSet": 55.3,
        "CO2Set": null,
        "O2Set": null,
        "FanSet": null
      }
    },
    {
      "timestamp": "2025-10-29T23:48:13.717836",
      "mode": "Timer",
      "readings": {
        "Temp1Read": 24.024,
        "HumRead": 55.45,
        "CO2Read": null,
        "O2Read": null,
        "FanRead": null
      },
      "setpoints": {
        "TempSet": 24.1,
        "HumSet": 55.3,
        "CO2Set": null,
        "O2Set": null,
        "FanSet": null
      }
    },
    {
      "timestamp": "2025-10-29T23:49:21.764349",
      "mode": "Timer",
      "readings": {
        "Temp1Read": 24.028,
        "HumRead": 55.512,
        "CO2Read": null,
        "O2Read": null,
        "FanRead": null
      },
      "setpoints": {
        "TempSet": 24.1,
        "HumSet": 55.3,
        "CO2Set": null,
        "O2Set": null,
        "FanSet": null
      }
    },
    {
      "timestamp": "2025-10-29T23:50:29.896235",
      "mode": "Timer",
      "readings": {
        "Temp1Read": 24.028,
        "HumRead": 55.388,
        "CO2Read": null,
        "O2Read": null,
        "FanRead": null
      },
      "setpoints": {
        "TempSet": 24.1,
        "HumSet": 55.3,
        "CO2Set": null,
        "O2Set": null,
        "FanSet": null
      }
    },
    {
      "timestamp": "2025-10-29T23:51:37.999379",
      "mode": "Timer",
      "readings": {
        "Temp1Read": 24.039,
        "HumRead": 55.543,
        "CO2Read": null,
        "O2Read": null,
        "FanRead": null
      },
      "setpoints": {
        "TempSet": 24.1,
        "HumSet": 55.3,
        "CO2Set": null,
        "O2Set": null,
        "FanSet": null
      }
    },
    {
      "timestamp": "2025-10-29T23:52:47.082760",
      "mode": "Timer",
      "readings": {
        "Temp1Read": 24.036,
        "HumRead": 55.482,
        "CO2Read": null,
        "O2Read": null,
        "FanRead": null
      },
      "setpoints": {
        "TempSet": 24.1,
        "HumSet": 55.3,
        "CO2Set": null,
        "O2Set": null,
        "FanSet": null
      }
    },
    {
      "timestamp": "2025-10-29T23:53:55.129615",
      "mode": "Timer",
      "readings": {
        "Temp1Read": 24.055,
        "HumRead": 55.482,
        "CO2Read": null,
        "O2Read": null,
        "FanRead": null
      },
      "setpoints": {
        "TempSet": 24.1,
        "HumSet": 55.3,
        "CO2Set": null,
        "O2Set": null,
        "FanSet": null
      }
    },
    {
      "timestamp": "2025-10-29T23:55:03.153852",
      "mode": "Timer",
      "readings": {
        "Temp1Read": 24.038,
        "HumRead": 55.514,
        "CO2Read": null,
        "O2Read": null,
        "FanRead": null
      },
      "setpoints": {
        "TempSet": 24.1,
        "HumSet": 55.3,
        "CO2Set": null,
        "O2Set": null,
        "FanSet": null
      }
    },
    {
      "timestamp": "2025-10-29T23:56:11.347830",
      "mode": "Timer",
      "readings": {
        "Temp1Read": 24.038,
        "HumRead": 55.39,
        "CO2Read": null,
        "O2Read": null,
        "FanRead": null
      },
      "setpoints": {
        "TempSet": 24.1,
        "HumSet": 55.3,
        "CO2Set": null,
        "O2Set": null,
        "FanSet": null
      }
    },
    {
      "timestamp": "2025-10-29T23:57:20.255317",
      "mode": "Timer",
      "readings": {
        "Temp1Read": 24.058,
        "HumRead": 55.298,
        "CO2Read": null,
        "O2Read": null,
        "FanRead": null
      },
      "setpoints": {
        "TempSet": 24.1,
        "HumSet": 55.3,
        "CO2Set": null,
        "O2Set": null,
        "FanSet": null
      }
    },
    {
      "timestamp": "2025-10-29T23:58:28.342911",
      "mode": "Timer",
      "readings": {
        "Temp1Read": 24.048,
        "HumRead": 55.268,
        "CO2Read": null,
        "O2Read": null,
        "FanRead": null
      },
      "setpoints": {
        "TempSet": 24.1,
        "HumSet": 55.3,
        "CO2Set": null,
        "O2Set": null,
        "FanSet": null
      }
    },
    {
      "timestamp": "2025-10-29T23:59:37.164953",
      "mode": "Timer",
      "readings": {
        "Temp1Read": 24.052,
        "HumRead": 55.331,
        "CO2Read": null,
        "O2Read": null,
        "FanRead": null
      },
      "setpoints": {
        "TempSet": 24.1,
        "HumSet": 55.3,
        "CO2Set": null,
        "O2Set": null,
        "FanSet": null
      }
    },
    {
      "timestamp": "2025-10-30T00:00:46.300864",
      "mode": "Timer",
      "readings": {
        "Temp1Read": 24.055,
        "HumRead": 55.207,
        "CO2Read": null,
        "O2Read": null,
        "FanRead": null
      },
      "setpoints": {
        "TempSet": 24.1,
        "HumSet": 55.3,
        "CO2Set": null,
        "O2Set": null,
        "FanSet": null
      }
    },
    {
      "timestamp": "2025-10-30T00:01:56.164056",
      "mode": "Timer",
      "readings": {
        "Temp1Read": 24.062,
        "HumRead": 55.238,
        "CO2Read": null,
        "O2Read": null,
        "FanRead": null
      },
      "setpoints": {
        "TempSet": 24.1,
        "HumSet": 55.3,
        "CO2Set": null,
        "O2Set": null,
        "FanSet": null
      }
    },
    {
      "timestamp": "2025-10-30T00:03:04.291225",
      "mode": "Timer",
      "readings": {
        "Temp1Read": 24.056,
        "HumRead": 55.208,
        "CO2Read": null,
        "O2Read": null,
        "FanRead": null
      },
      "setpoints": {
        "TempSet": 24.1,
        "HumSet": 55.3,
        "CO2Set": null,
        "O2Set": null,
        "FanSet": null
      }
    },
    {
      "timestamp": "2025-10-30T00:04:14.250695",
      "mode": "Timer",
      "readings": {
        "Temp1Read": 24.079,
        "HumRead": 55.147,
        "CO2Read": null,
        "O2Read": null,
        "FanRead": null
      },
      "setpoints": {
        "TempSet": 24.1,
        "HumSet": 55.3,
        "CO2Set": null,
        "O2Set": null,
        "FanSet": null
      }
    },
    {
      "timestamp": "2025-10-30T00:05:24.480406",
      "mode": "Timer",
      "readings": {
        "Temp1Read": 24.067,
        "HumRead": 55.117,
        "CO2Read": null,
        "O2Read": null,
        "FanRead": null
      },
      "setpoints": {
        "TempSet": 24.1,
        "HumSet": 55.3,
        "CO2Set": null,
        "O2Set": null,
        "FanSet": null
      }
    },
    {
      "timestamp": "2025-10-30T00:06:33.494182",
      "mode": "Timer",
      "readings": {
        "Temp1Read": 24.082,
        "HumRead": 55.178,
        "CO2Read": null,
        "O2Read": null,
        "FanRead": null
      },
      "setpoints": {
        "TempSet": 24.1,
        "HumSet": 55.3,
        "CO2Set": null,
        "O2Set": null,
        "FanSet": null
      }
    },
    {
      "timestamp": "2025-10-30T00:07:42.653307",
      "mode": "Timer",
      "readings": {
        "Temp1Read": 24.079,
        "HumRead": 55.179,
        "CO2Read": null,
        "O2Read": null,
        "FanRead": null
      },
      "setpoints": {
        "TempSet": 24.1,
        "HumSet": 55.3,
        "CO2Set": null,
        "O2Set": null,
        "FanSet": null
      }
    },
    {
      "timestamp": "2025-10-30T00:08:51.303801",
      "mode": "Timer",
      "readings": {
        "Temp1Read": 24.088,
        "HumRead": 55.179,
        "CO2Read": null,
        "O2Read": null,
        "FanRead": null
      },
      "setpoints": {
        "TempSet": 24.1,
        "HumSet": 55.3,
        "CO2Set": null,
        "O2Set": null,
        "FanSet": null
      }
    },
    {
      "timestamp": "2025-10-30T00:10:00.063534",
      "mode": "Timer",
      "readings": {
        "Temp1Read": 24.083,
        "HumRead": 55.087,
        "CO2Read": null,
        "O2Read": null,
        "FanRead": null
      },
      "setpoints": {
        "TempSet": 24.1,
        "HumSet": 55.3,
        "CO2Set": null,
        "O2Set": null,
        "FanSet": null
      }
    },
    {
      "timestamp": "2025-10-30T00:11:09.395251",
      "mode": "Timer",
      "readings": {
        "Temp1Read": 24.086,
        "HumRead": 55.026,
        "CO2Read": null,
        "O2Read": null,
        "FanRead": null
      },
      "setpoints": {
        "TempSet": 24.1,
        "HumSet": 55.3,
        "CO2Set": null,
        "O2Set": null,
        "FanSet": null
      }
    },
    {
      "timestamp": "2025-10-30T00:12:17.591784",
      "mode": "Timer",
      "readings": {
        "Temp1Read": 24.083,
        "HumRead": 55.118,
        "CO2Read": null,
        "O2Read": null,
        "FanRead": null
      },
      "setpoints": {
        "TempSet": 24.1,
        "HumSet": 55.3,
        "CO2Set": null,
        "O2Set": null,
        "FanSet": null
      }
    },
    {
      "timestamp": "2025-10-30T00:13:25.781889",
      "mode": "Timer",
      "readings": {
        "Temp1Read": 24.083,
        "HumRead": 55.027,
        "CO2Read": null,
        "O2Read": null,
        "FanRead": null
      },
      "setpoints": {
        "TempSet": 24.1,
        "HumSet": 55.3,
        "CO2Set": null,
        "O2Set": null,
        "FanSet": null
      }
    },
    {
      "timestamp": "2025-10-30T00:14:35.762914",
      "mode": "Timer",
      "readings": {
        "Temp1Read": 24.1,
        "HumRead": 55.027,
        "CO2Read": null,
        "O2Read": null,
        "FanRead": null
      },
      "setpoints": {
        "TempSet": 24.1,
        "HumSet": 55.3,
        "CO2Set": null,
        "O2Set": null,
        "FanSet": null
      }
    },
    {
      "timestamp": "2025-10-30T00:15:44.118480",
      "mode": "Timer",
      "readings": {
        "Temp1Read": 24.083,
        "HumRead": 55.119,
        "CO2Read": null,
        "O2Read": null,
        "FanRead": null
      },
      "setpoints": {
        "TempSet": 24.1,
        "HumSet": 55.3,
        "CO2Set": null,
        "O2Set": null,
        "FanSet": null
      }
    },
    {
      "timestamp": "2025-10-30T00:16:52.889309",
      "mode": "Timer",
      "readings": {
        "Temp1Read": 24.097,
        "HumRead": 54.997,
        "CO2Read": null,
        "O2Read": null,
        "FanRead": null
      },
      "setpoints": {
        "TempSet": 24.1,
        "HumSet": 55.3,
        "CO2Set": null,
        "O2Set": null,
        "FanSet": null
      }
    },
    {
      "timestamp": "2025-10-30T00:18:01.035167",
      "mode": "Timer",
      "readings": {
        "Temp1Read": 24.076,
        "HumRead": 55.027,
        "CO2Read": null,
        "O2Read": null,
        "FanRead": null
      },
      "setpoints": {
        "TempSet": 24.1,
        "HumSet": 55.3,
        "CO2Set": null,
        "O2Set": null,
        "FanSet": null
      }
    },
    {
      "timestamp": "2025-10-30T00:19:10.992845",
      "mode": "Timer",
      "readings": {
        "Temp1Read": 24.087,
        "HumRead": 55.058,
        "CO2Read": null,
        "O2Read": null,
        "FanRead": null
      },
      "setpoints": {
        "TempSet": 24.1,
        "HumSet": 55.3,
        "CO2Set": null,
        "O2Set": null,
        "FanSet": null
      }
    },
    {
      "timestamp": "2025-10-30T00:20:20.085579",
      "mode": "Timer",
      "readings": {
        "Temp1Read": 24.086,
        "HumRead": 55.058,
        "CO2Read": null,
        "O2Read": null,
        "FanRead": null
      },
      "setpoints": {
        "TempSet": 24.1,
        "HumSet": 55.3,
        "CO2Set": null,
        "O2Set": null,
        "FanSet": null
      }
    },
    {
      "timestamp": "2025-10-30T00:21:28.818945",
      "mode": "Timer",
      "readings": {
        "Temp1Read": 24.093,
        "HumRead": 54.997,
        "CO2Read": null,
        "O2Read": null,
        "FanRead": null
      },
      "setpoints": {
        "TempSet": 24.1,
        "HumSet": 55.3,
        "CO2Set": null,
        "O2Set": null,
        "FanSet": null
      }
    },
    {
      "timestamp": "2025-10-30T00:22:38.935658",
      "mode": "Timer",
      "readings": {
        "Temp1Read": 24.084,
        "HumRead": 54.997,
        "CO2Read": null,
        "O2Read": null,
        "FanRead": null
      },
      "setpoints": {
        "TempSet": 24.1,
        "HumSet": 55.3,
        "CO2Set": null,
        "O2Set": null,
        "FanSet": null
      }
    },
    {
      "timestamp": "2025-10-30T00:23:48.894119",
      "mode": "Timer",
      "readings": {
        "Temp1Read": 24.094,
        "HumRead": 55.208,
        "CO2Read": null,
        "O2Read": null,
        "FanRead": null
      },
      "setpoints": {
        "TempSet": 24.1,
        "HumSet": 55.3,
        "CO2Set": null,
        "O2Set": null,
        "FanSet": null
      }
    },
    {
      "timestamp": "2025-10-30T00:24:59.012081",
      "mode": "Timer",
      "readings": {
        "Temp1Read": 24.106,
        "HumRead": 56.112,
        "CO2Read": null,
        "O2Read": null,
        "FanRead": null
      },
      "setpoints": {
        "TempSet": 24.1,
        "HumSet": 55.3,
        "CO2Set": null,
        "O2Set": null,
        "FanSet": null
      }
    },
    {
      "timestamp": "2025-10-30T00:26:07.188606",
      "mode": "Timer",
      "readings": {
        "Temp1Read": 24.106,
        "HumRead": 56.296,
        "CO2Read": null,
        "O2Read": null,
        "FanRead": null
      },
      "setpoints": {
        "TempSet": 24.1,
        "HumSet": 55.3,
        "CO2Set": null,
        "O2Set": null,
        "FanSet": null
      }
    },
    {
      "timestamp": "2025-10-30T00:27:15.122328",
      "mode": "Timer",
      "readings": {
        "Temp1Read": 24.11,
        "HumRead": 56.235,
        "CO2Read": null,
        "O2Read": null,
        "FanRead": null
      },
      "setpoints": {
        "TempSet": 24.1,
        "HumSet": 55.3,
        "CO2Set": null,
        "O2Set": null,
        "FanSet": null
      }
    },
    {
      "timestamp": "2025-10-30T00:28:24.005725",
      "mode": "Timer",
      "readings": {
        "Temp1Read": 24.114,
        "HumRead": 56.145,
        "CO2Read": null,
        "O2Read": null,
        "FanRead": null
      },
      "setpoints": {
        "TempSet": 24.1,
        "HumSet": 55.3,
        "CO2Set": null,
        "O2Set": null,
        "FanSet": null
      }
    },
    {
      "timestamp": "2025-10-30T00:29:33.034652",
      "mode": "Timer",
      "readings": {
        "Temp1Read": 24.121,
        "HumRead": 56.023,
        "CO2Read": null,
        "O2Read": null,
        "FanRead": null
      },
      "setpoints": {
        "TempSet": 24.1,
        "HumSet": 55.3,
        "CO2Set": null,
        "O2Set": null,
        "FanSet": null
      }
    },
    {
      "timestamp": "2025-10-30T00:30:41.621645",
      "mode": "Timer",
      "readings": {
        "Temp1Read": 24.126,
        "HumRead": 55.872,
        "CO2Read": null,
        "O2Read": null,
        "FanRead": null
      },
      "setpoints": {
        "TempSet": 24.1,
        "HumSet": 55.3,
        "CO2Set": null,
        "O2Set": null,
        "FanSet": null
      }
    },
    {
      "timestamp": "2025-10-30T00:31:50.160832",
      "mode": "Timer",
      "readings": {
        "Temp1Read": 24.121,
        "HumRead": 55.813,
        "CO2Read": null,
        "O2Read": null,
        "FanRead": null
      },
      "setpoints": {
        "TempSet": 24.1,
        "HumSet": 55.3,
        "CO2Set": null,
        "O2Set": null,
        "FanSet": null
      }
    },
    {
      "timestamp": "2025-10-30T00:32:58.355995",
      "mode": "Timer",
      "readings": {
        "Temp1Read": 24.122,
        "HumRead": 55.755,
        "CO2Read": null,
        "O2Read": null,
        "FanRead": null
      },
      "setpoints": {
        "TempSet": 24.1,
        "HumSet": 55.3,
        "CO2Set": null,
        "O2Set": null,
        "FanSet": null
      }
    },
    {
      "timestamp": "2025-10-30T00:34:07.348147",
      "mode": "Timer",
      "readings": {
        "Temp1Read": 24.13,
        "HumRead": 55.571,
        "CO2Read": null,
        "O2Read": null,
        "FanRead": null
      },
      "setpoints": {
        "TempSet": 24.1,
        "HumSet": 55.3,
        "CO2Set": null,
        "O2Set": null,
        "FanSet": null
      }
    },
    {
      "timestamp": "2025-10-30T00:35:15.677409",
      "mode": "Timer",
      "readings": {
        "Temp1Read": 24.127,
        "HumRead": 55.539,
        "CO2Read": null,
        "O2Read": null,
        "FanRead": null
      },
      "setpoints": {
        "TempSet": 24.1,
        "HumSet": 55.3,
        "CO2Set": null,
        "O2Set": null,
        "FanSet": null
      }
    },
    {
      "timestamp": "2025-10-30T00:36:25.359391",
      "mode": "Timer",
      "readings": {
        "Temp1Read": 24.122,
        "HumRead": 55.601,
        "CO2Read": null,
        "O2Read": null,
        "FanRead": null
      },
      "setpoints": {
        "TempSet": 24.1,
        "HumSet": 55.3,
        "CO2Set": null,
        "O2Set": null,
        "FanSet": null
      }
    },
    {
      "timestamp": "2025-10-30T00:37:33.398989",
      "mode": "Timer",
      "readings": {
        "Temp1Read": 24.124,
        "HumRead": 55.632,
        "CO2Read": null,
        "O2Read": null,
        "FanRead": null
      },
      "setpoints": {
        "TempSet": 24.1,
        "HumSet": 55.3,
        "CO2Set": null,
        "O2Set": null,
        "FanSet": null
      }
    },
    {
      "timestamp": "2025-10-30T00:38:42.751785",
      "mode": "Timer",
      "readings": {
        "Temp1Read": 24.137,
        "HumRead": 55.571,
        "CO2Read": null,
        "O2Read": null,
        "FanRead": null
      },
      "setpoints": {
        "TempSet": 24.1,
        "HumSet": 55.3,
        "CO2Set": null,
        "O2Set": null,
        "FanSet": null
      }
    },
    {
      "timestamp": "2025-10-30T00:39:51.962027",
      "mode": "Timer",
      "readings": {
        "Temp1Read": 24.135,
        "HumRead": 55.664,
        "CO2Read": null,
        "O2Read": null,
        "FanRead": null
      },
      "setpoints": {
        "TempSet": 24.1,
        "HumSet": 55.3,
        "CO2Set": null,
        "O2Set": null,
        "FanSet": null
      }
    },
    {
      "timestamp": "2025-10-30T00:41:00.352866",
      "mode": "Timer",
      "readings": {
        "Temp1Read": 24.124,
        "HumRead": 55.509,
        "CO2Read": null,
        "O2Read": null,
        "FanRead": null
      },
      "setpoints": {
        "TempSet": 24.1,
        "HumSet": 55.3,
        "CO2Set": null,
        "O2Set": null,
        "FanSet": null
      }
    },
    {
      "timestamp": "2025-10-30T00:42:09.345061",
      "mode": "Timer",
      "readings": {
        "Temp1Read": 24.127,
        "HumRead": 55.572,
        "CO2Read": null,
        "O2Read": null,
        "FanRead": null
      },
      "setpoints": {
        "TempSet": 24.1,
        "HumSet": 55.3,
        "CO2Set": null,
        "O2Set": null,
        "FanSet": null
      }
    },
    {
      "timestamp": "2025-10-30T00:43:17.376895",
      "mode": "Timer",
      "readings": {
        "Temp1Read": 24.127,
        "HumRead": 55.633,
        "CO2Read": null,
        "O2Read": null,
        "FanRead": null
      },
      "setpoints": {
        "TempSet": 24.1,
        "HumSet": 55.3,
        "CO2Set": null,
        "O2Set": null,
        "FanSet": null
      }
    },
    {
      "timestamp": "2025-10-30T00:44:25.680168",
      "mode": "Timer",
      "readings": {
        "Temp1Read": 24.128,
        "HumRead": 55.571,
        "CO2Read": null,
        "O2Read": null,
        "FanRead": null
      },
      "setpoints": {
        "TempSet": 24.1,
        "HumSet": 55.3,
        "CO2Set": null,
        "O2Set": null,
        "FanSet": null
      }
    },
    {
      "timestamp": "2025-10-30T00:45:34.737562",
      "mode": "Timer",
      "readings": {
        "Temp1Read": 24.121,
        "HumRead": 55.54,
        "CO2Read": null,
        "O2Read": null,
        "FanRead": null
      },
      "setpoints": {
        "TempSet": 24.1,
        "HumSet": 55.3,
        "CO2Set": null,
        "O2Set": null,
        "FanSet": null
      }
    },
    {
      "timestamp": "2025-10-30T00:46:42.849416",
      "mode": "Timer",
      "readings": {
        "Temp1Read": 24.124,
        "HumRead": 55.633,
        "CO2Read": null,
        "O2Read": null,
        "FanRead": null
      },
      "setpoints": {
        "TempSet": 24.1,
        "HumSet": 55.3,
        "CO2Set": null,
        "O2Set": null,
        "FanSet": null
      }
    },
    {
      "timestamp": "2025-10-30T00:47:53.036168",
      "mode": "Timer",
      "readings": {
        "Temp1Read": 24.133,
        "HumRead": 55.542,
        "CO2Read": null,
        "O2Read": null,
        "FanRead": null
      },
      "setpoints": {
        "TempSet": 24.1,
        "HumSet": 55.3,
        "CO2Set": null,
        "O2Set": null,
        "FanSet": null
      }
    },
    {
      "timestamp": "2025-10-30T00:49:01.488682",
      "mode": "Timer",
      "readings": {
        "Temp1Read": 24.131,
        "HumRead": 55.542,
        "CO2Read": null,
        "O2Read": null,
        "FanRead": null
      },
      "setpoints": {
        "TempSet": 24.1,
        "HumSet": 55.3,
        "CO2Set": null,
        "O2Set": null,
        "FanSet": null
      }
    },
    {
      "timestamp": "2025-10-30T00:50:12.382636",
      "mode": "Timer",
      "readings": {
        "Temp1Read": 24.124,
        "HumRead": 55.418,
        "CO2Read": null,
        "O2Read": null,
        "FanRead": null
      },
      "setpoints": {
        "TempSet": 24.1,
        "HumSet": 55.3,
        "CO2Set": null,
        "O2Set": null,
        "FanSet": null
      }
    },
    {
      "timestamp": "2025-10-30T00:51:21.651405",
      "mode": "Timer",
      "readings": {
        "Temp1Read": 24.143,
        "HumRead": 55.511,
        "CO2Read": null,
        "O2Read": null,
        "FanRead": null
      },
      "setpoints": {
        "TempSet": 24.1,
        "HumSet": 55.3,
        "CO2Set": null,
        "O2Set": null,
        "FanSet": null
      }
    },
    {
      "timestamp": "2025-10-30T00:52:31.314603",
      "mode": "Timer",
      "readings": {
        "Temp1Read": 24.121,
        "HumRead": 55.511,
        "CO2Read": null,
        "O2Read": null,
        "FanRead": null
      },
      "setpoints": {
        "TempSet": 24.1,
        "HumSet": 55.3,
        "CO2Set": null,
        "O2Set": null,
        "FanSet": null
      }
    },
    {
      "timestamp": "2025-10-30T00:53:40.463360",
      "mode": "Timer",
      "readings": {
        "Temp1Read": 24.143,
        "HumRead": 55.48,
        "CO2Read": null,
        "O2Read": null,
        "FanRead": null
      },
      "setpoints": {
        "TempSet": 24.1,
        "HumSet": 55.3,
        "CO2Set": null,
        "O2Set": null,
        "FanSet": null
      }
    },
    {
      "timestamp": "2025-10-30T00:54:49.535565",
      "mode": "Timer",
      "readings": {
        "Temp1Read": 24.124,
        "HumRead": 55.542,
        "CO2Read": null,
        "O2Read": null,
        "FanRead": null
      },
      "setpoints": {
        "TempSet": 24.1,
        "HumSet": 55.3,
        "CO2Set": null,
        "O2Set": null,
        "FanSet": null
      }
    },
    {
      "timestamp": "2025-10-30T00:55:58.154260",
      "mode": "Timer",
      "readings": {
        "Temp1Read": 24.117,
        "HumRead": 55.48,
        "CO2Read": null,
        "O2Read": null,
        "FanRead": null
      },
      "setpoints": {
        "TempSet": 24.1,
        "HumSet": 55.3,
        "CO2Set": null,
        "O2Set": null,
        "FanSet": null
      }
    },
    {
      "timestamp": "2025-10-30T00:57:07.389781",
      "mode": "Timer",
      "readings": {
        "Temp1Read": 24.107,
        "HumRead": 55.542,
        "CO2Read": null,
        "O2Read": null,
        "FanRead": null
      },
      "setpoints": {
        "TempSet": 24.1,
        "HumSet": 55.3,
        "CO2Set": null,
        "O2Set": null,
        "FanSet": null
      }
    },
    {
      "timestamp": "2025-10-30T00:58:16.196009",
      "mode": "Timer",
      "readings": {
        "Temp1Read": 24.114,
        "HumRead": 55.573,
        "CO2Read": null,
        "O2Read": null,
        "FanRead": null
      },
      "setpoints": {
        "TempSet": 24.1,
        "HumSet": 55.3,
        "CO2Set": null,
        "O2Set": null,
        "FanSet": null
      }
    },
    {
      "timestamp": "2025-10-30T00:59:25.155267",
      "mode": "Timer",
      "readings": {
        "Temp1Read": 24.118,
        "HumRead": 55.542,
        "CO2Read": null,
        "O2Read": null,
        "FanRead": null
      },
      "setpoints": {
        "TempSet": 24.1,
        "HumSet": 55.3,
        "CO2Set": null,
        "O2Set": null,
        "FanSet": null
      }
    },
    {
      "timestamp": "2025-10-30T01:00:34.179924",
      "mode": "Timer",
      "readings": {
        "Temp1Read": 24.111,
        "HumRead": 55.48,
        "CO2Read": null,
        "O2Read": null,
        "FanRead": null
      },
      "setpoints": {
        "TempSet": 24.1,
        "HumSet": 55.3,
        "CO2Set": null,
        "O2Set": null,
        "FanSet": null
      }
    },
    {
      "timestamp": "2025-10-30T01:01:43.173503",
      "mode": "Timer",
      "readings": {
        "Temp1Read": 24.104,
        "HumRead": 55.543,
        "CO2Read": null,
        "O2Read": null,
        "FanRead": null
      },
      "setpoints": {
        "TempSet": 24.1,
        "HumSet": 55.3,
        "CO2Set": null,
        "O2Set": null,
        "FanSet": null
      }
    },
    {
      "timestamp": "2025-10-30T01:02:53.111389",
      "mode": "Timer",
      "readings": {
        "Temp1Read": 24.106,
        "HumRead": 55.481,
        "CO2Read": null,
        "O2Read": null,
        "FanRead": null
      },
      "setpoints": {
        "TempSet": 24.1,
        "HumSet": 55.3,
        "CO2Set": null,
        "O2Set": null,
        "FanSet": null
      }
    },
    {
      "timestamp": "2025-10-30T01:04:02.038971",
      "mode": "Timer",
      "readings": {
        "Temp1Read": 24.113,
        "HumRead": 55.449,
        "CO2Read": null,
        "O2Read": null,
        "FanRead": null
      },
      "setpoints": {
        "TempSet": 24.1,
        "HumSet": 55.3,
        "CO2Set": null,
        "O2Set": null,
        "FanSet": null
      }
    },
    {
      "timestamp": "2025-10-30T01:05:10.326127",
      "mode": "Timer",
      "readings": {
        "Temp1Read": 24.118,
        "HumRead": 55.481,
        "CO2Read": null,
        "O2Read": null,
        "FanRead": null
      },
      "setpoints": {
        "TempSet": 24.1,
        "HumSet": 55.3,
        "CO2Set": null,
        "O2Set": null,
        "FanSet": null
      }
    },
    {
      "timestamp": "2025-10-30T01:06:19.526482",
      "mode": "Timer",
      "readings": {
        "Temp1Read": 24.108,
        "HumRead": 55.481,
        "CO2Read": null,
        "O2Read": null,
        "FanRead": null
      },
      "setpoints": {
        "TempSet": 24.1,
        "HumSet": 55.3,
        "CO2Set": null,
        "O2Set": null,
        "FanSet": null
      }
    },
    {
      "timestamp": "2025-10-30T01:07:27.811426",
      "mode": "Timer",
      "readings": {
        "Temp1Read": 24.113,
        "HumRead": 55.481,
        "CO2Read": null,
        "O2Read": null,
        "FanRead": null
      },
      "setpoints": {
        "TempSet": 24.1,
        "HumSet": 55.3,
        "CO2Set": null,
        "O2Set": null,
        "FanSet": null
      }
    },
    {
      "timestamp": "2025-10-30T01:08:35.900697",
      "mode": "Timer",
      "readings": {
        "Temp1Read": 24.1,
        "HumRead": 55.419,
        "CO2Read": null,
        "O2Read": null,
        "FanRead": null
      },
      "setpoints": {
        "TempSet": 24.1,
        "HumSet": 55.3,
        "CO2Set": null,
        "O2Set": null,
        "FanSet": null
      }
    },
    {
      "timestamp": "2025-10-30T01:09:44.852687",
      "mode": "Timer",
      "readings": {
        "Temp1Read": 24.095,
        "HumRead": 55.481,
        "CO2Read": null,
        "O2Read": null,
        "FanRead": null
      },
      "setpoints": {
        "TempSet": 24.1,
        "HumSet": 55.3,
        "CO2Set": null,
        "O2Set": null,
        "FanSet": null
      }
    },
    {
      "timestamp": "2025-10-30T01:10:54.530235",
      "mode": "Timer",
      "readings": {
        "Temp1Read": 24.104,
        "HumRead": 55.419,
        "CO2Read": null,
        "O2Read": null,
        "FanRead": null
      },
      "setpoints": {
        "TempSet": 24.1,
        "HumSet": 55.3,
        "CO2Set": null,
        "O2Set": null,
        "FanSet": null
      }
    },
    {
      "timestamp": "2025-10-30T01:12:02.804374",
      "mode": "Timer",
      "readings": {
        "Temp1Read": 24.113,
        "HumRead": 55.512,
        "CO2Read": null,
        "O2Read": null,
        "FanRead": null
      },
      "setpoints": {
        "TempSet": 24.1,
        "HumSet": 55.3,
        "CO2Set": null,
        "O2Set": null,
        "FanSet": null
      }
    },
    {
      "timestamp": "2025-10-30T01:13:12.873237",
      "mode": "Timer",
      "readings": {
        "Temp1Read": 24.099,
        "HumRead": 55.512,
        "CO2Read": null,
        "O2Read": null,
        "FanRead": null
      },
      "setpoints": {
        "TempSet": 24.1,
        "HumSet": 55.3,
        "CO2Set": null,
        "O2Set": null,
        "FanSet": null
      }
    },
    {
      "timestamp": "2025-10-30T01:14:21.053298",
      "mode": "Timer",
      "readings": {
        "Temp1Read": 24.114,
        "HumRead": 55.481,
        "CO2Read": null,
        "O2Read": null,
        "FanRead": null
      },
      "setpoints": {
        "TempSet": 24.1,
        "HumSet": 55.3,
        "CO2Set": null,
        "O2Set": null,
        "FanSet": null
      }
    },
    {
      "timestamp": "2025-10-30T01:15:30.199984",
      "mode": "Timer",
      "readings": {
        "Temp1Read": 24.1,
        "HumRead": 55.359,
        "CO2Read": null,
        "O2Read": null,
        "FanRead": null
      },
      "setpoints": {
        "TempSet": 24.1,
        "HumSet": 55.3,
        "CO2Set": null,
        "O2Set": null,
        "FanSet": null
      }
    },
    {
      "timestamp": "2025-10-30T01:16:41.244326",
      "mode": "Timer",
      "readings": {
        "Temp1Read": 24.095,
        "HumRead": 55.389,
        "CO2Read": null,
        "O2Read": null,
        "FanRead": null
      },
      "setpoints": {
        "TempSet": 24.1,
        "HumSet": 55.3,
        "CO2Set": null,
        "O2Set": null,
        "FanSet": null
      }
    },
    {
      "timestamp": "2025-10-30T01:17:50.261900",
      "mode": "Timer",
      "readings": {
        "Temp1Read": 24.104,
        "HumRead": 55.389,
        "CO2Read": null,
        "O2Read": null,
        "FanRead": null
      },
      "setpoints": {
        "TempSet": 24.1,
        "HumSet": 55.3,
        "CO2Set": null,
        "O2Set": null,
        "FanSet": null
      }
    },
    {
      "timestamp": "2025-10-30T01:18:59.273950",
      "mode": "Timer",
      "readings": {
        "Temp1Read": 24.095,
        "HumRead": 55.421,
        "CO2Read": null,
        "O2Read": null,
        "FanRead": null
      },
      "setpoints": {
        "TempSet": 24.1,
        "HumSet": 55.3,
        "CO2Set": null,
        "O2Set": null,
        "FanSet": null
      }
    },
    {
      "timestamp": "2025-10-30T01:20:07.325372",
      "mode": "Timer",
      "readings": {
        "Temp1Read": 24.1,
        "HumRead": 55.328,
        "CO2Read": null,
        "O2Read": null,
        "FanRead": null
      },
      "setpoints": {
        "TempSet": 24.1,
        "HumSet": 55.3,
        "CO2Set": null,
        "O2Set": null,
        "FanSet": null
      }
    },
    {
      "timestamp": "2025-10-30T01:21:16.308938",
      "mode": "Timer",
      "readings": {
        "Temp1Read": 24.09,
        "HumRead": 55.421,
        "CO2Read": null,
        "O2Read": null,
        "FanRead": null
      },
      "setpoints": {
        "TempSet": 24.1,
        "HumSet": 55.3,
        "CO2Set": null,
        "O2Set": null,
        "FanSet": null
      }
    },
    {
      "timestamp": "2025-10-30T01:22:25.149477",
      "mode": "Timer",
      "readings": {
        "Temp1Read": 24.09,
        "HumRead": 55.421,
        "CO2Read": null,
        "O2Read": null,
        "FanRead": null
      },
      "setpoints": {
        "TempSet": 24.1,
        "HumSet": 55.3,
        "CO2Set": null,
        "O2Set": null,
        "FanSet": null
      }
    },
    {
      "timestamp": "2025-10-30T01:23:34.896507",
      "mode": "Timer",
      "readings": {
        "Temp1Read": 24.087,
        "HumRead": 55.421,
        "CO2Read": null,
        "O2Read": null,
        "FanRead": null
      },
      "setpoints": {
        "TempSet": 24.1,
        "HumSet": 55.3,
        "CO2Set": null,
        "O2Set": null,
        "FanSet": null
      }
    }
  ]
}