{
  "metadata": {
    "created": "2025-10-23T15:49:03.021959",
    "device_ip": "192.168.100.100:80",
    "max_hours": 3.0,
    "description": "Rolling history of Memmert incubator data",
    "last_updated": "2025-10-31T08:53:48.626826",
    "total_entries": 143,
    "time_span_hours": 2.99
  },
  "data": [
    {
      "timestamp": "2025-10-31T05:54:18.261450",
      "mode": "Timer",
      "readings": {
        "Temp1Read": 29.606,
        "HumRead": 59.06,
        "CO2Read": null,
        "O2Read": null,
        "FanRead": null,
        "TempSensor1Read": 30.286,
        "TempSensor2Read": 31.202,
        "TempSensor3Read": 31.004
      },
      "setpoints": {
        "TempSet": 29.6,
        "HumSet": 58.6,
        "CO2Set": null,
        "O2Set": null,
        "FanSet": null
      }
    },
    {
      "timestamp": "2025-10-31T05:55:31.754991",
      "mode": "Timer",
      "readings": {
        "Temp1Read": 29.605,
        "HumRead": 58.877,
        "CO2Read": null,
        "O2Read": null,
        "FanRead": null,
        "TempSensor1Read": 30.289,
        "TempSensor2Read": 31.205,
        "TempSensor3Read": 31.004
      },
      "setpoints": {
        "TempSet": 29.6,
        "HumSet": 58.6,
        "CO2Set": null,
        "O2Set": null,
        "FanSet": null
      }
    },
    {
      "timestamp": "2025-10-31T05:56:44.333008",
      "mode": "Timer",
      "readings": {
        "Temp1Read": 29.601,
        "HumRead": 58.879,
        "CO2Read": null,
        "O2Read": null,
        "FanRead": null,
        "TempSensor1Read": 30.289,
        "TempSensor2Read": 31.208,
        "TempSensor3Read": 31.006
      },
      "setpoints": {
        "TempSet": 29.6,
        "HumSet": 58.6,
        "CO2Set": null,
        "O2Set": null,
        "FanSet": null
      }
    },
    {
      "timestamp": "2025-10-31T05:57:56.841219",
      "mode": "Timer",
      "readings": {
        "Temp1Read": 29.603,
        "HumRead": 58.691,
        "CO2Read": null,
        "O2Read": null,
        "FanRead": null,
        "TempSensor1Read": 30.289,
        "TempSensor2Read": 31.21,
        "TempSensor3Read": 31.007
      },
      "setpoints": {
        "TempSet": 29.6,
        "HumSet": 58.6,
        "CO2Set": null,
        "O2Set": null,
        "FanSet": null
      }
    },
    {
      "timestamp": "2025-10-31T05:59:09.219481",
      "mode": "Timer",
      "readings": {
        "Temp1Read": 29.591,
        "HumRead": 58.695,
        "CO2Read": null,
        "O2Read": null,
        "FanRead": null,
        "TempSensor1Read": 30.29,
        "TempSensor2Read": 31.213,
        "TempSensor3Read": 31.007
      },
      "setpoints": {
        "TempSet": 29.6,
        "HumSet": 58.6,
        "CO2Set": null,
        "O2Set": null,
        "FanSet": null
      }
    },
    {
      "timestamp": "2025-10-31T06:00:22.468729",
      "mode": "Timer",
      "readings": {
        "Temp1Read": 29.597,
        "HumRead": 58.633,
        "CO2Read": null,
        "O2Read": null,
        "FanRead": null,
        "TempSensor1Read": 30.29,
        "TempSensor2Read": 31.216,
        "TempSensor3Read": 31.008
      },
      "setpoints": {
        "TempSet": 29.6,
        "HumSet": 58.6,
        "CO2Set": null,
        "O2Set": null,
        "FanSet": null
      }
    },
    {
      "timestamp": "2025-10-31T06:01:35.122257",
      "mode": "Timer",
      "readings": {
        "Temp1Read": 29.611,
        "HumRead": 58.729,
        "CO2Read": null,
        "O2Read": null,
        "FanRead": null,
        "TempSensor1Read": 30.292,
        "TempSensor2Read": 31.22,
        "TempSensor3Read": 31.007
      },
      "setpoints": {
        "TempSet": 29.6,
        "HumSet": 58.6,
        "CO2Set": null,
        "O2Set": null,
        "FanSet": null
      }
    },
    {
      "timestamp": "2025-10-31T06:02:49.593246",
      "mode": "Timer",
      "readings": {
        "Temp1Read": 29.598,
        "HumRead": 58.606,
        "CO2Read": null,
        "O2Read": null,
        "FanRead": null,
        "TempSensor1Read": 30.291,
        "TempSensor2Read": 31.224,
        "TempSensor3Read": 31.01
      },
      "setpoints": {
        "TempSet": 29.6,
        "HumSet": 58.6,
        "CO2Set": null,
        "O2Set": null,
        "FanSet": null
      }
    },
    {
      "timestamp": "2025-10-31T06:04:02.612319",
      "mode": "Timer",
      "readings": {
        "Temp1Read": 29.61,
        "HumRead": 58.579,
        "CO2Read": null,
        "O2Read": null,
        "FanRead": null,
        "TempSensor1Read": 30.291,
        "TempSensor2Read": 31.228,
        "TempSensor3Read": 31.013
      },
      "setpoints": {
        "TempSet": 29.6,
        "HumSet": 58.6,
        "CO2Set": null,
        "O2Set": null,
        "FanSet": null
      }
    },
    {
      "timestamp": "2025-10-31T06:05:16.108332",
      "mode": "Timer",
      "readings": {
        "Temp1Read": 29.61,
        "HumRead": 58.487,
        "CO2Read": null,
        "O2Read": null,
        "FanRead": null,
        "TempSensor1Read": 30.292,
        "TempSensor2Read": 31.232,
        "TempSensor3Read": 31.013
      },
      "setpoints": {
        "TempSet": 29.6,
        "HumSet": 58.6,
        "CO2Set": null,
        "O2Set": null,
        "FanSet": null
      }
    },
    {
      "timestamp": "2025-10-31T06:06:29.328624",
      "mode": "Timer",
      "readings": {
        "Temp1Read": 29.611,
        "HumRead": 58.323,
        "CO2Read": null,
        "O2Read": null,
        "FanRead": null,
        "TempSensor1Read": 30.293,
        "TempSensor2Read": 31.236,
        "TempSensor3Read": 31.013
      },
      "setpoints": {
        "TempSet": 29.6,
        "HumSet": 58.6,
        "CO2Set": null,
        "O2Set": null,
        "FanSet": null
      }
    },
    {
      "timestamp": "2025-10-31T06:07:42.473864",
      "mode": "Timer",
      "readings": {
        "Temp1Read": 29.626,
        "HumRead": 58.232,
        "CO2Read": null,
        "O2Read": null,
        "FanRead": null,
        "TempSensor1Read": 30.295,
        "TempSensor2Read": 31.24,
        "TempSensor3Read": 31.016
      },
      "setpoints": {
        "TempSet": 29.6,
        "HumSet": 58.6,
        "CO2Set": null,
        "O2Set": null,
        "FanSet": null
      }
    },
    {
      "timestamp": "2025-10-31T06:08:55.099615",
      "mode": "Timer",
      "readings": {
        "Temp1Read": 29.616,
        "HumRead": 58.902,
        "CO2Read": null,
        "O2Read": null,
        "FanRead": null,
        "TempSensor1Read": 30.296,
        "TempSensor2Read": 31.244,
        "TempSensor3Read": 31.018
      },
      "setpoints": {
        "TempSet": 29.6,
        "HumSet": 58.6,
        "CO2Set": null,
        "O2Set": null,
        "FanSet": null
      }
    },
    {
      "timestamp": "2025-10-31T06:10:07.477752",
      "mode": "Timer",
      "readings": {
        "Temp1Read": 29.629,
        "HumRead": 59.055,
        "CO2Read": null,
        "O2Read": null,
        "FanRead": null,
        "TempSensor1Read": 30.297,
        "TempSensor2Read": 31.248,
        "TempSensor3Read": 31.018
      },
      "setpoints": {
        "TempSet": 29.6,
        "HumSet": 58.6,
        "CO2Set": null,
        "O2Set": null,
        "FanSet": null
      }
    },
    {
      "timestamp": "2025-10-31T06:11:19.748134",
      "mode": "Timer",
      "readings": {
        "Temp1Read": 29.618,
        "HumRead": 58.783,
        "CO2Read": null,
        "O2Read": null,
        "FanRead": null,
        "TempSensor1Read": 30.299,
        "TempSensor2Read": 31.254,
        "TempSensor3Read": 31.02
      },
      "setpoints": {
        "TempSet": 29.6,
        "HumSet": 58.6,
        "CO2Set": null,
        "O2Set": null,
        "FanSet": null
      }
    },
    {
      "timestamp": "2025-10-31T06:12:31.635131",
      "mode": "Timer",
      "readings": {
        "Temp1Read": 29.611,
        "HumRead": 58.91,
        "CO2Read": null,
        "O2Read": null,
        "FanRead": null,
        "TempSensor1Read": 30.301,
        "TempSensor2Read": 31.263,
        "TempSensor3Read": 31.021
      },
      "setpoints": {
        "TempSet": 29.6,
        "HumSet": 58.6,
        "CO2Set": null,
        "O2Set": null,
        "FanSet": null
      }
    },
    {
      "timestamp": "2025-10-31T06:13:45.026475",
      "mode": "Timer",
      "readings": {
        "Temp1Read": 29.616,
        "HumRead": 58.94,
        "CO2Read": null,
        "O2Read": null,
        "FanRead": null,
        "TempSensor1Read": 30.304,
        "TempSensor2Read": 31.273,
        "TempSensor3Read": 31.023
      },
      "setpoints": {
        "TempSet": 29.6,
        "HumSet": 58.6,
        "CO2Set": null,
        "O2Set": null,
        "FanSet": null
      }
    },
    {
      "timestamp": "2025-10-31T06:14:59.470945",
      "mode": "Timer",
      "readings": {
        "Temp1Read": 29.627,
        "HumRead": 58.849,
        "CO2Read": null,
        "O2Read": null,
        "FanRead": null,
        "TempSensor1Read": 30.306,
        "TempSensor2Read": 31.286,
        "TempSensor3Read": 31.025
      },
      "setpoints": {
        "TempSet": 29.6,
        "HumSet": 58.6,
        "CO2Set": null,
        "O2Set": null,
        "FanSet": null
      }
    },
    {
      "timestamp": "2025-10-31T06:16:11.994961",
      "mode": "Timer",
      "readings": {
        "Temp1Read": 29.622,
        "HumRead": 58.693,
        "CO2Read": null,
        "O2Read": null,
        "FanRead": null,
        "TempSensor1Read": 30.308,
        "TempSensor2Read": 31.441,
        "TempSensor3Read": 31.027
      },
      "setpoints": {
        "TempSet": 29.6,
        "HumSet": 58.6,
        "CO2Set": null,
        "O2Set": null,
        "FanSet": null
      }
    },
    {
      "timestamp": "2025-10-31T06:17:24.952900",
      "mode": "Timer",
      "readings": {
        "Temp1Read": 29.627,
        "HumRead": 58.726,
        "CO2Read": null,
        "O2Read": null,
        "FanRead": null,
        "TempSensor1Read": 30.31,
        "TempSensor2Read": 31.443,
        "TempSensor3Read": 31.026
      },
      "setpoints": {
        "TempSet": 29.6,
        "HumSet": 58.6,
        "CO2Set": null,
        "O2Set": null,
        "FanSet": null
      }
    },
    {
      "timestamp": "2025-10-31T06:18:38.358651",
      "mode": "Timer",
      "readings": {
        "Temp1Read": 29.623,
        "HumRead": 58.666,
        "CO2Read": null,
        "O2Read": null,
        "FanRead": null,
        "TempSensor1Read": 30.31,
        "TempSensor2Read": 31.449,
        "TempSensor3Read": 31.029
      },
      "setpoints": {
        "TempSet": 29.6,
        "HumSet": 58.6,
        "CO2Set": null,
        "O2Set": null,
        "FanSet": null
      }
    },
    {
      "timestamp": "2025-10-31T06:19:50.903589",
      "mode": "Timer",
      "readings": {
        "Temp1Read": 29.62,
        "HumRead": 58.606,
        "CO2Read": null,
        "O2Read": null,
        "FanRead": null,
        "TempSensor1Read": 30.313,
        "TempSensor2Read": 31.45,
        "TempSensor3Read": 31.03
      },
      "setpoints": {
        "TempSet": 29.6,
        "HumSet": 58.6,
        "CO2Set": null,
        "O2Set": null,
        "FanSet": null
      }
    },
    {
      "timestamp": "2025-10-31T06:21:04.256211",
      "mode": "Timer",
      "readings": {
        "Temp1Read": 29.616,
        "HumRead": 58.515,
        "CO2Read": null,
        "O2Read": null,
        "FanRead": null,
        "TempSensor1Read": 30.313,
        "TempSensor2Read": 31.451,
        "TempSensor3Read": 31.032
      },
      "setpoints": {
        "TempSet": 29.6,
        "HumSet": 58.6,
        "CO2Set": null,
        "O2Set": null,
        "FanSet": null
      }
    },
    {
      "timestamp": "2025-10-31T06:22:16.275677",
      "mode": "Timer",
      "readings": {
        "Temp1Read": 29.616,
        "HumRead": 58.518,
        "CO2Read": null,
        "O2Read": null,
        "FanRead": null,
        "TempSensor1Read": 30.317,
        "TempSensor2Read": 31.441,
        "TempSensor3Read": 31.032
      },
      "setpoints": {
        "TempSet": 29.6,
        "HumSet": 58.6,
        "CO2Set": null,
        "O2Set": null,
        "FanSet": null
      }
    },
    {
      "timestamp": "2025-10-31T06:23:29.974145",
      "mode": "Timer",
      "readings": {
        "Temp1Read": 29.605,
        "HumRead": 58.458,
        "CO2Read": null,
        "O2Read": null,
        "FanRead": null,
        "TempSensor1Read": 30.316,
        "TempSensor2Read": 31.412,
        "TempSensor3Read": 31.032
      },
      "setpoints": {
        "TempSet": 29.6,
        "HumSet": 58.6,
        "CO2Set": null,
        "O2Set": null,
        "FanSet": null
      }
    },
    {
      "timestamp": "2025-10-31T06:24:43.329448",
      "mode": "Timer",
      "readings": {
        "Temp1Read": 29.61,
        "HumRead": 58.388,
        "CO2Read": null,
        "O2Read": null,
        "FanRead": null,
        "TempSensor1Read": 30.315,
        "TempSensor2Read": 31.207,
        "TempSensor3Read": 31.031
      },
      "setpoints": {
        "TempSet": 29.6,
        "HumSet": 58.6,
        "CO2Set": null,
        "O2Set": null,
        "FanSet": null
      }
    },
    {
      "timestamp": "2025-10-31T06:25:56.659263",
      "mode": "Timer",
      "readings": {
        "Temp1Read": 29.603,
        "HumRead": 58.549,
        "CO2Read": null,
        "O2Read": null,
        "FanRead": null,
        "TempSensor1Read": 30.314,
        "TempSensor2Read": 31.209,
        "TempSensor3Read": 31.031
      },
      "setpoints": {
        "TempSet": 29.6,
        "HumSet": 58.6,
        "CO2Set": null,
        "O2Set": null,
        "FanSet": null
      }
    },
    {
      "timestamp": "2025-10-31T06:27:10.914968",
      "mode": "Timer",
      "readings": {
        "Temp1Read": 29.614,
        "HumRead": 58.994,
        "CO2Read": null,
        "O2Read": null,
        "FanRead": null,
        "TempSensor1Read": 30.315,
        "TempSensor2Read": 31.221,
        "TempSensor3Read": 31.031
      },
      "setpoints": {
        "TempSet": 29.6,
        "HumSet": 58.6,
        "CO2Set": null,
        "O2Set": null,
        "FanSet": null
      }
    },
    {
      "timestamp": "2025-10-31T06:28:23.436635",
      "mode": "Timer",
      "readings": {
        "Temp1Read": 29.613,
        "HumRead": 58.907,
        "CO2Read": null,
        "O2Read": null,
        "FanRead": null,
        "TempSensor1Read": 30.315,
        "TempSensor2Read": 31.357,
        "TempSensor3Read": 31.032
      },
      "setpoints": {
        "TempSet": 29.6,
        "HumSet": 58.6,
        "CO2Set": null,
        "O2Set": null,
        "FanSet": null
      }
    },
    {
      "timestamp": "2025-10-31T06:29:36.343020",
      "mode": "Timer",
      "readings": {
        "Temp1Read": 29.605,
        "HumRead": 58.877,
        "CO2Read": null,
        "O2Read": null,
        "FanRead": null,
        "TempSensor1Read": 30.315,
        "TempSensor2Read": 31.364,
        "TempSensor3Read": 31.031
      },
      "setpoints": {
        "TempSet": 29.6,
        "HumSet": 58.6,
        "CO2Set": null,
        "O2Set": null,
        "FanSet": null
      }
    },
    {
      "timestamp": "2025-10-31T06:30:48.610021",
      "mode": "Timer",
      "readings": {
        "Temp1Read": 29.62,
        "HumRead": 58.784,
        "CO2Read": null,
        "O2Read": null,
        "FanRead": null,
        "TempSensor1Read": 30.315,
        "TempSensor2Read": 31.373,
        "TempSensor3Read": 31.03
      },
      "setpoints": {
        "TempSet": 29.6,
        "HumSet": 58.6,
        "CO2Set": null,
        "O2Set": null,
        "FanSet": null
      }
    },
    {
      "timestamp": "2025-10-31T06:32:01.260384",
      "mode": "Timer",
      "readings": {
        "Temp1Read": 29.623,
        "HumRead": 58.786,
        "CO2Read": null,
        "O2Read": null,
        "FanRead": null,
        "TempSensor1Read": 30.316,
        "TempSensor2Read": 31.377,
        "TempSensor3Read": 31.03
      },
      "setpoints": {
        "TempSet": 29.6,
        "HumSet": 58.6,
        "CO2Set": null,
        "O2Set": null,
        "FanSet": null
      }
    },
    {
      "timestamp": "2025-10-31T06:33:14.605806",
      "mode": "Timer",
      "readings": {
        "Temp1Read": 29.602,
        "HumRead": 58.754,
        "CO2Read": null,
        "O2Read": null,
        "FanRead": null,
        "TempSensor1Read": 30.314,
        "TempSensor2Read": 31.397,
        "TempSensor3Read": 31.029
      },
      "setpoints": {
        "TempSet": 29.6,
        "HumSet": 58.6,
        "CO2Set": null,
        "O2Set": null,
        "FanSet": null
      }
    },
    {
      "timestamp": "2025-10-31T06:34:27.077401",
      "mode": "Timer",
      "readings": {
        "Temp1Read": 29.594,
        "HumRead": 58.789,
        "CO2Read": null,
        "O2Read": null,
        "FanRead": null,
        "TempSensor1Read": 30.315,
        "TempSensor2Read": 31.407,
        "TempSensor3Read": 31.029
      },
      "setpoints": {
        "TempSet": 29.6,
        "HumSet": 58.6,
        "CO2Set": null,
        "O2Set": null,
        "FanSet": null
      }
    },
    {
      "timestamp": "2025-10-31T06:35:41.436524",
      "mode": "Timer",
      "readings": {
        "Temp1Read": 29.611,
        "HumRead": 58.759,
        "CO2Read": null,
        "O2Read": null,
        "FanRead": null,
        "TempSensor1Read": 30.315,
        "TempSensor2Read": 31.4,
        "TempSensor3Read": 31.028
      },
      "setpoints": {
        "TempSet": 29.6,
        "HumSet": 58.6,
        "CO2Set": null,
        "O2Set": null,
        "FanSet": null
      }
    },
    {
      "timestamp": "2025-10-31T06:36:54.083590",
      "mode": "Timer",
      "readings": {
        "Temp1Read": 29.607,
        "HumRead": 58.605,
        "CO2Read": null,
        "O2Read": null,
        "FanRead": null,
        "TempSensor1Read": 30.313,
        "TempSensor2Read": 31.388,
        "TempSensor3Read": 31.028
      },
      "setpoints": {
        "TempSet": 29.6,
        "HumSet": 58.6,
        "CO2Set": null,
        "O2Set": null,
        "FanSet": null
      }
    },
    {
      "timestamp": "2025-10-31T06:38:06.525517",
      "mode": "Timer",
      "readings": {
        "Temp1Read": 29.618,
        "HumRead": 58.639,
        "CO2Read": null,
        "O2Read": null,
        "FanRead": null,
        "TempSensor1Read": 30.313,
        "TempSensor2Read": 31.251,
        "TempSensor3Read": 31.028
      },
      "setpoints": {
        "TempSet": 29.6,
        "HumSet": 58.6,
        "CO2Set": null,
        "O2Set": null,
        "FanSet": null
      }
    },
    {
      "timestamp": "2025-10-31T06:39:18.877321",
      "mode": "Timer",
      "readings": {
        "Temp1Read": 29.602,
        "HumRead": 58.609,
        "CO2Read": null,
        "O2Read": null,
        "FanRead": null,
        "TempSensor1Read": 30.314,
        "TempSensor2Read": 31.259,
        "TempSensor3Read": 31.026
      },
      "setpoints": {
        "TempSet": 29.6,
        "HumSet": 58.6,
        "CO2Set": null,
        "O2Set": null,
        "FanSet": null
      }
    },
    {
      "timestamp": "2025-10-31T06:40:30.449164",
      "mode": "Timer",
      "readings": {
        "Temp1Read": 29.601,
        "HumRead": 58.425,
        "CO2Read": null,
        "O2Read": null,
        "FanRead": null,
        "TempSensor1Read": 30.313,
        "TempSensor2Read": 31.276,
        "TempSensor3Read": 31.024
      },
      "setpoints": {
        "TempSet": 29.6,
        "HumSet": 58.6,
        "CO2Set": null,
        "O2Set": null,
        "FanSet": null
      }
    },
    {
      "timestamp": "2025-10-31T06:41:43.922187",
      "mode": "Timer",
      "readings": {
        "Temp1Read": 29.605,
        "HumRead": 58.263,
        "CO2Read": null,
        "O2Read": null,
        "FanRead": null,
        "TempSensor1Read": 30.313,
        "TempSensor2Read": 31.274,
        "TempSensor3Read": 31.025
      },
      "setpoints": {
        "TempSet": 29.6,
        "HumSet": 58.6,
        "CO2Set": null,
        "O2Set": null,
        "FanSet": null
      }
    },
    {
      "timestamp": "2025-10-31T06:42:57.581530",
      "mode": "Timer",
      "readings": {
        "Temp1Read": 29.61,
        "HumRead": 58.939,
        "CO2Read": null,
        "O2Read": null,
        "FanRead": null,
        "TempSensor1Read": 30.311,
        "TempSensor2Read": 31.252,
        "TempSensor3Read": 31.024
      },
      "setpoints": {
        "TempSet": 29.6,
        "HumSet": 58.6,
        "CO2Set": null,
        "O2Set": null,
        "FanSet": null
      }
    },
    {
      "timestamp": "2025-10-31T06:44:11.246314",
      "mode": "Timer",
      "readings": {
        "Temp1Read": 29.598,
        "HumRead": 58.994,
        "CO2Read": null,
        "O2Read": null,
        "FanRead": null,
        "TempSensor1Read": 30.31,
        "TempSensor2Read": 31.23,
        "TempSensor3Read": 31.024
      },
      "setpoints": {
        "TempSet": 29.6,
        "HumSet": 58.6,
        "CO2Set": null,
        "O2Set": null,
        "FanSet": null
      }
    },
    {
      "timestamp": "2025-10-31T06:45:23.776058",
      "mode": "Timer",
      "readings": {
        "Temp1Read": 29.613,
        "HumRead": 58.753,
        "CO2Read": null,
        "O2Read": null,
        "FanRead": null,
        "TempSensor1Read": 30.309,
        "TempSensor2Read": 31.211,
        "TempSensor3Read": 31.025
      },
      "setpoints": {
        "TempSet": 29.6,
        "HumSet": 58.6,
        "CO2Set": null,
        "O2Set": null,
        "FanSet": null
      }
    },
    {
      "timestamp": "2025-10-31T06:46:35.429988",
      "mode": "Timer",
      "readings": {
        "Temp1Read": 29.601,
        "HumRead": 58.753,
        "CO2Read": null,
        "O2Read": null,
        "FanRead": null,
        "TempSensor1Read": 30.309,
        "TempSensor2Read": 31.2,
        "TempSensor3Read": 31.025
      },
      "setpoints": {
        "TempSet": 29.6,
        "HumSet": 58.6,
        "CO2Set": null,
        "O2Set": null,
        "FanSet": null
      }
    },
    {
      "timestamp": "2025-10-31T06:47:48.055006",
      "mode": "Timer",
      "readings": {
        "Temp1Read": 29.594,
        "HumRead": 58.817,
        "CO2Read": null,
        "O2Read": null,
        "FanRead": null,
        "TempSensor1Read": 30.309,
        "TempSensor2Read": 31.194,
        "TempSensor3Read": 31.022
      },
      "setpoints": {
        "TempSet": 29.6,
        "HumSet": 58.6,
        "CO2Set": null,
        "O2Set": null,
        "FanSet": null
      }
    },
    {
      "timestamp": "2025-10-31T06:48:59.786243",
      "mode": "Timer",
      "readings": {
        "Temp1Read": 29.607,
        "HumRead": 58.786,
        "CO2Read": null,
        "O2Read": null,
        "FanRead": null,
        "TempSensor1Read": 30.307,
        "TempSensor2Read": 31.192,
        "TempSensor3Read": 31.022
      },
      "setpoints": {
        "TempSet": 29.6,
        "HumSet": 58.6,
        "CO2Set": null,
        "O2Set": null,
        "FanSet": null
      }
    },
    {
      "timestamp": "2025-10-31T06:50:13.353285",
      "mode": "Timer",
      "readings": {
        "Temp1Read": 29.602,
        "HumRead": 58.695,
        "CO2Read": null,
        "O2Read": null,
        "FanRead": null,
        "TempSensor1Read": 30.309,
        "TempSensor2Read": 31.195,
        "TempSensor3Read": 31.022
      },
      "setpoints": {
        "TempSet": 29.6,
        "HumSet": 58.6,
        "CO2Set": null,
        "O2Set": null,
        "FanSet": null
      }
    },
    {
      "timestamp": "2025-10-31T06:51:26.555909",
      "mode": "Timer",
      "readings": {
        "Temp1Read": 29.593,
        "HumRead": 58.757,
        "CO2Read": null,
        "O2Read": null,
        "FanRead": null,
        "TempSensor1Read": 30.31,
        "TempSensor2Read": 31.203,
        "TempSensor3Read": 31.021
      },
      "setpoints": {
        "TempSet": 29.6,
        "HumSet": 58.6,
        "CO2Set": null,
        "O2Set": null,
        "FanSet": null
      }
    },
    {
      "timestamp": "2025-10-31T06:52:40.208971",
      "mode": "Timer",
      "readings": {
        "Temp1Read": 29.614,
        "HumRead": 58.76,
        "CO2Read": null,
        "O2Read": null,
        "FanRead": null,
        "TempSensor1Read": 30.309,
        "TempSensor2Read": 31.213,
        "TempSensor3Read": 31.021
      },
      "setpoints": {
        "TempSet": 29.6,
        "HumSet": 58.6,
        "CO2Set": null,
        "O2Set": null,
        "FanSet": null
      }
    },
    {
      "timestamp": "2025-10-31T06:53:52.698063",
      "mode": "Timer",
      "readings": {
        "Temp1Read": 29.603,
        "HumRead": 58.638,
        "CO2Read": null,
        "O2Read": null,
        "FanRead": null,
        "TempSensor1Read": 30.309,
        "TempSensor2Read": 31.222,
        "TempSensor3Read": 31.02
      },
      "setpoints": {
        "TempSet": 29.6,
        "HumSet": 58.6,
        "CO2Set": null,
        "O2Set": null,
        "FanSet": null
      }
    },
    {
      "timestamp": "2025-10-31T06:55:04.651098",
      "mode": "Timer",
      "readings": {
        "Temp1Read": 29.613,
        "HumRead": 58.608,
        "CO2Read": null,
        "O2Read": null,
        "FanRead": null,
        "TempSensor1Read": 30.307,
        "TempSensor2Read": 31.234,
        "TempSensor3Read": 31.02
      },
      "setpoints": {
        "TempSet": 29.6,
        "HumSet": 58.6,
        "CO2Set": null,
        "O2Set": null,
        "FanSet": null
      }
    },
    {
      "timestamp": "2025-10-31T06:56:17.304976",
      "mode": "Timer",
      "readings": {
        "Temp1Read": 29.614,
        "HumRead": 58.643,
        "CO2Read": null,
        "O2Read": null,
        "FanRead": null,
        "TempSensor1Read": 30.306,
        "TempSensor2Read": 31.243,
        "TempSensor3Read": 31.018
      },
      "setpoints": {
        "TempSet": 29.6,
        "HumSet": 58.6,
        "CO2Set": null,
        "O2Set": null,
        "FanSet": null
      }
    },
    {
      "timestamp": "2025-10-31T06:57:29.845475",
      "mode": "Timer",
      "readings": {
        "Temp1Read": 29.606,
        "HumRead": 58.448,
        "CO2Read": null,
        "O2Read": null,
        "FanRead": null,
        "TempSensor1Read": 30.306,
        "TempSensor2Read": 31.25,
        "TempSensor3Read": 31.017
      },
      "setpoints": {
        "TempSet": 29.6,
        "HumSet": 58.6,
        "CO2Set": null,
        "O2Set": null,
        "FanSet": null
      }
    },
    {
      "timestamp": "2025-10-31T06:58:42.474949",
      "mode": "Timer",
      "readings": {
        "Temp1Read": 29.601,
        "HumRead": 58.43,
        "CO2Read": null,
        "O2Read": null,
        "FanRead": null,
        "TempSensor1Read": 30.304,
        "TempSensor2Read": 31.256,
        "TempSensor3Read": 31.017
      },
      "setpoints": {
        "TempSet": 29.6,
        "HumSet": 58.6,
        "CO2Set": null,
        "O2Set": null,
        "FanSet": null
      }
    },
    {
      "timestamp": "2025-10-31T06:59:55.039210",
      "mode": "Timer",
      "readings": {
        "Temp1Read": 29.603,
        "HumRead": 58.432,
        "CO2Read": null,
        "O2Read": null,
        "FanRead": null,
        "TempSensor1Read": 30.305,
        "TempSensor2Read": 31.263,
        "TempSensor3Read": 31.016
      },
      "setpoints": {
        "TempSet": 29.6,
        "HumSet": 58.6,
        "CO2Set": null,
        "O2Set": null,
        "FanSet": null
      }
    },
    {
      "timestamp": "2025-10-31T07:01:08.512719",
      "mode": "Timer",
      "readings": {
        "Temp1Read": 29.599,
        "HumRead": 58.846,
        "CO2Read": null,
        "O2Read": null,
        "FanRead": null,
        "TempSensor1Read": 30.303,
        "TempSensor2Read": 31.267,
        "TempSensor3Read": 31.016
      },
      "setpoints": {
        "TempSet": 29.6,
        "HumSet": 58.6,
        "CO2Set": null,
        "O2Set": null,
        "FanSet": null
      }
    },
    {
      "timestamp": "2025-10-31T07:02:21.134627",
      "mode": "Timer",
      "readings": {
        "Temp1Read": 29.605,
        "HumRead": 59.029,
        "CO2Read": null,
        "O2Read": null,
        "FanRead": null,
        "TempSensor1Read": 30.303,
        "TempSensor2Read": 31.27,
        "TempSensor3Read": 31.016
      },
      "setpoints": {
        "TempSet": 29.6,
        "HumSet": 58.6,
        "CO2Set": null,
        "O2Set": null,
        "FanSet": null
      }
    },
    {
      "timestamp": "2025-10-31T07:03:32.822469",
      "mode": "Timer",
      "readings": {
        "Temp1Read": 29.605,
        "HumRead": 58.939,
        "CO2Read": null,
        "O2Read": null,
        "FanRead": null,
        "TempSensor1Read": 30.301,
        "TempSensor2Read": 31.267,
        "TempSensor3Read": 31.018
      },
      "setpoints": {
        "TempSet": 29.6,
        "HumSet": 58.6,
        "CO2Set": null,
        "O2Set": null,
        "FanSet": null
      }
    },
    {
      "timestamp": "2025-10-31T07:04:46.095249",
      "mode": "Timer",
      "readings": {
        "Temp1Read": 29.607,
        "HumRead": 58.94,
        "CO2Read": null,
        "O2Read": null,
        "FanRead": null,
        "TempSensor1Read": 30.301,
        "TempSensor2Read": 31.263,
        "TempSensor3Read": 31.019
      },
      "setpoints": {
        "TempSet": 29.6,
        "HumSet": 58.6,
        "CO2Set": null,
        "O2Set": null,
        "FanSet": null
      }
    },
    {
      "timestamp": "2025-10-31T07:06:00.232405",
      "mode": "Timer",
      "readings": {
        "Temp1Read": 29.598,
        "HumRead": 58.847,
        "CO2Read": null,
        "O2Read": null,
        "FanRead": null,
        "TempSensor1Read": 30.3,
        "TempSensor2Read": 31.258,
        "TempSensor3Read": 31.017
      },
      "setpoints": {
        "TempSet": 29.6,
        "HumSet": 58.6,
        "CO2Set": null,
        "O2Set": null,
        "FanSet": null
      }
    },
    {
      "timestamp": "2025-10-31T07:07:12.672028",
      "mode": "Timer",
      "readings": {
        "Temp1Read": 29.611,
        "HumRead": 58.755,
        "CO2Read": null,
        "O2Read": null,
        "FanRead": null,
        "TempSensor1Read": 30.3,
        "TempSensor2Read": 31.254,
        "TempSensor3Read": 31.017
      },
      "setpoints": {
        "TempSet": 29.6,
        "HumSet": 58.6,
        "CO2Set": null,
        "O2Set": null,
        "FanSet": null
      }
    },
    {
      "timestamp": "2025-10-31T07:08:26.143833",
      "mode": "Timer",
      "readings": {
        "Temp1Read": 29.601,
        "HumRead": 58.786,
        "CO2Read": null,
        "O2Read": null,
        "FanRead": null,
        "TempSensor1Read": 30.3,
        "TempSensor2Read": 31.248,
        "TempSensor3Read": 31.016
      },
      "setpoints": {
        "TempSet": 29.6,
        "HumSet": 58.6,
        "CO2Set": null,
        "O2Set": null,
        "FanSet": null
      }
    },
    {
      "timestamp": "2025-10-31T07:09:39.057411",
      "mode": "Timer",
      "readings": {
        "Temp1Read": 29.603,
        "HumRead": 58.789,
        "CO2Read": null,
        "O2Read": null,
        "FanRead": null,
        "TempSensor1Read": 30.302,
        "TempSensor2Read": 31.244,
        "TempSensor3Read": 31.015
      },
      "setpoints": {
        "TempSet": 29.6,
        "HumSet": 58.6,
        "CO2Set": null,
        "O2Set": null,
        "FanSet": null
      }
    },
    {
      "timestamp": "2025-10-31T07:10:51.677628",
      "mode": "Timer",
      "readings": {
        "Temp1Read": 29.616,
        "HumRead": 58.759,
        "CO2Read": null,
        "O2Read": null,
        "FanRead": null,
        "TempSensor1Read": 30.301,
        "TempSensor2Read": 31.239,
        "TempSensor3Read": 31.015
      },
      "setpoints": {
        "TempSet": 29.6,
        "HumSet": 58.6,
        "CO2Set": null,
        "O2Set": null,
        "FanSet": null
      }
    },
    {
      "timestamp": "2025-10-31T07:12:03.415476",
      "mode": "Timer",
      "readings": {
        "Temp1Read": 29.605,
        "HumRead": 58.636,
        "CO2Read": null,
        "O2Read": null,
        "FanRead": null,
        "TempSensor1Read": 30.302,
        "TempSensor2Read": 31.236,
        "TempSensor3Read": 31.015
      },
      "setpoints": {
        "TempSet": 29.6,
        "HumSet": 58.6,
        "CO2Set": null,
        "O2Set": null,
        "FanSet": null
      }
    },
    {
      "timestamp": "2025-10-31T07:13:15.446870",
      "mode": "Timer",
      "readings": {
        "Temp1Read": 29.599,
        "HumRead": 58.669,
        "CO2Read": null,
        "O2Read": null,
        "FanRead": null,
        "TempSensor1Read": 30.3,
        "TempSensor2Read": 31.234,
        "TempSensor3Read": 31.016
      },
      "setpoints": {
        "TempSet": 29.6,
        "HumSet": 58.6,
        "CO2Set": null,
        "O2Set": null,
        "FanSet": null
      }
    },
    {
      "timestamp": "2025-10-31T07:14:28.091621",
      "mode": "Timer",
      "readings": {
        "Temp1Read": 29.607,
        "HumRead": 58.672,
        "CO2Read": null,
        "O2Read": null,
        "FanRead": null,
        "TempSensor1Read": 30.302,
        "TempSensor2Read": 31.231,
        "TempSensor3Read": 31.015
      },
      "setpoints": {
        "TempSet": 29.6,
        "HumSet": 58.6,
        "CO2Set": null,
        "O2Set": null,
        "FanSet": null
      }
    },
    {
      "timestamp": "2025-10-31T07:15:39.924065",
      "mode": "Timer",
      "readings": {
        "Temp1Read": 29.618,
        "HumRead": 58.424,
        "CO2Read": null,
        "O2Read": null,
        "FanRead": null,
        "TempSensor1Read": 30.298,
        "TempSensor2Read": 31.229,
        "TempSensor3Read": 31.016
      },
      "setpoints": {
        "TempSet": 29.6,
        "HumSet": 58.6,
        "CO2Set": null,
        "O2Set": null,
        "FanSet": null
      }
    },
    {
      "timestamp": "2025-10-31T07:16:53.632880",
      "mode": "Timer",
      "readings": {
        "Temp1Read": 29.609,
        "HumRead": 58.46,
        "CO2Read": null,
        "O2Read": null,
        "FanRead": null,
        "TempSensor1Read": 30.297,
        "TempSensor2Read": 31.226,
        "TempSensor3Read": 31.015
      },
      "setpoints": {
        "TempSet": 29.6,
        "HumSet": 58.6,
        "CO2Set": null,
        "O2Set": null,
        "FanSet": null
      }
    },
    {
      "timestamp": "2025-10-31T07:18:07.164663",
      "mode": "Timer",
      "readings": {
        "Temp1Read": 29.607,
        "HumRead": 58.368,
        "CO2Read": null,
        "O2Read": null,
        "FanRead": null,
        "TempSensor1Read": 30.297,
        "TempSensor2Read": 31.221,
        "TempSensor3Read": 31.014
      },
      "setpoints": {
        "TempSet": 29.6,
        "HumSet": 58.6,
        "CO2Set": null,
        "O2Set": null,
        "FanSet": null
      }
    },
    {
      "timestamp": "2025-10-31T07:19:20.689991",
      "mode": "Timer",
      "readings": {
        "Temp1Read": 29.605,
        "HumRead": 58.328,
        "CO2Read": null,
        "O2Read": null,
        "FanRead": null,
        "TempSensor1Read": 30.298,
        "TempSensor2Read": 31.217,
        "TempSensor3Read": 31.014
      },
      "setpoints": {
        "TempSet": 29.6,
        "HumSet": 58.6,
        "CO2Set": null,
        "O2Set": null,
        "FanSet": null
      }
    },
    {
      "timestamp": "2025-10-31T07:20:35.238465",
      "mode": "Timer",
      "readings": {
        "Temp1Read": 29.611,
        "HumRead": 59.141,
        "CO2Read": null,
        "O2Read": null,
        "FanRead": null,
        "TempSensor1Read": 30.299,
        "TempSensor2Read": 31.21,
        "TempSensor3Read": 31.013
      },
      "setpoints": {
        "TempSet": 29.6,
        "HumSet": 58.6,
        "CO2Set": null,
        "O2Set": null,
        "FanSet": null
      }
    },
    {
      "timestamp": "2025-10-31T07:21:47.478210",
      "mode": "Timer",
      "readings": {
        "Temp1Read": 29.603,
        "HumRead": 59.085,
        "CO2Read": null,
        "O2Read": null,
        "FanRead": null,
        "TempSensor1Read": 30.299,
        "TempSensor2Read": 31.204,
        "TempSensor3Read": 31.013
      },
      "setpoints": {
        "TempSet": 29.6,
        "HumSet": 58.6,
        "CO2Set": null,
        "O2Set": null,
        "FanSet": null
      }
    },
    {
      "timestamp": "2025-10-31T07:23:00.905741",
      "mode": "Timer",
      "readings": {
        "Temp1Read": 29.593,
        "HumRead": 58.877,
        "CO2Read": null,
        "O2Read": null,
        "FanRead": null,
        "TempSensor1Read": 30.3,
        "TempSensor2Read": 31.197,
        "TempSensor3Read": 31.013
      },
      "setpoints": {
        "TempSet": 29.6,
        "HumSet": 58.6,
        "CO2Set": null,
        "O2Set": null,
        "FanSet": null
      }
    },
    {
      "timestamp": "2025-10-31T07:24:12.591702",
      "mode": "Timer",
      "readings": {
        "Temp1Read": 29.593,
        "HumRead": 58.879,
        "CO2Read": null,
        "O2Read": null,
        "FanRead": null,
        "TempSensor1Read": 30.301,
        "TempSensor2Read": 31.191,
        "TempSensor3Read": 31.014
      },
      "setpoints": {
        "TempSet": 29.6,
        "HumSet": 58.6,
        "CO2Set": null,
        "O2Set": null,
        "FanSet": null
      }
    },
    {
      "timestamp": "2025-10-31T07:25:25.052061",
      "mode": "Timer",
      "readings": {
        "Temp1Read": 29.585,
        "HumRead": 58.753,
        "CO2Read": null,
        "O2Read": null,
        "FanRead": null,
        "TempSensor1Read": 30.302,
        "TempSensor2Read": 31.187,
        "TempSensor3Read": 31.014
      },
      "setpoints": {
        "TempSet": 29.6,
        "HumSet": 58.6,
        "CO2Set": null,
        "O2Set": null,
        "FanSet": null
      }
    },
    {
      "timestamp": "2025-10-31T07:26:37.629881",
      "mode": "Timer",
      "readings": {
        "Temp1Read": 29.591,
        "HumRead": 58.849,
        "CO2Read": null,
        "O2Read": null,
        "FanRead": null,
        "TempSensor1Read": 30.3,
        "TempSensor2Read": 31.182,
        "TempSensor3Read": 31.013
      },
      "setpoints": {
        "TempSet": 29.6,
        "HumSet": 58.6,
        "CO2Set": null,
        "O2Set": null,
        "FanSet": null
      }
    },
    {
      "timestamp": "2025-10-31T07:27:49.923427",
      "mode": "Timer",
      "readings": {
        "Temp1Read": 29.598,
        "HumRead": 58.754,
        "CO2Read": null,
        "O2Read": null,
        "FanRead": null,
        "TempSensor1Read": 30.302,
        "TempSensor2Read": 31.179,
        "TempSensor3Read": 31.013
      },
      "setpoints": {
        "TempSet": 29.6,
        "HumSet": 58.6,
        "CO2Set": null,
        "O2Set": null,
        "FanSet": null
      }
    },
    {
      "timestamp": "2025-10-31T07:29:02.739427",
      "mode": "Timer",
      "readings": {
        "Temp1Read": 29.594,
        "HumRead": 58.787,
        "CO2Read": null,
        "O2Read": null,
        "FanRead": null,
        "TempSensor1Read": 30.301,
        "TempSensor2Read": 31.176,
        "TempSensor3Read": 31.013
      },
      "setpoints": {
        "TempSet": 29.6,
        "HumSet": 58.6,
        "CO2Set": null,
        "O2Set": null,
        "FanSet": null
      }
    },
    {
      "timestamp": "2025-10-31T07:30:14.299979",
      "mode": "Timer",
      "readings": {
        "Temp1Read": 29.583,
        "HumRead": 58.757,
        "CO2Read": null,
        "O2Read": null,
        "FanRead": null,
        "TempSensor1Read": 30.301,
        "TempSensor2Read": 31.172,
        "TempSensor3Read": 31.01
      },
      "setpoints": {
        "TempSet": 29.6,
        "HumSet": 58.6,
        "CO2Set": null,
        "O2Set": null,
        "FanSet": null
      }
    },
    {
      "timestamp": "2025-10-31T07:31:26.176791",
      "mode": "Timer",
      "readings": {
        "Temp1Read": 29.593,
        "HumRead": 58.635,
        "CO2Read": null,
        "O2Read": null,
        "FanRead": null,
        "TempSensor1Read": 30.303,
        "TempSensor2Read": 31.169,
        "TempSensor3Read": 31.008
      },
      "setpoints": {
        "TempSet": 29.6,
        "HumSet": 58.6,
        "CO2Set": null,
        "O2Set": null,
        "FanSet": null
      }
    },
    {
      "timestamp": "2025-10-31T07:32:38.763467",
      "mode": "Timer",
      "readings": {
        "Temp1Read": 29.577,
        "HumRead": 58.699,
        "CO2Read": null,
        "O2Read": null,
        "FanRead": null,
        "TempSensor1Read": 30.302,
        "TempSensor2Read": 31.166,
        "TempSensor3Read": 31.007
      },
      "setpoints": {
        "TempSet": 29.6,
        "HumSet": 58.6,
        "CO2Set": null,
        "O2Set": null,
        "FanSet": null
      }
    },
    {
      "timestamp": "2025-10-31T07:33:51.020509",
      "mode": "Timer",
      "readings": {
        "Temp1Read": 29.578,
        "HumRead": 58.576,
        "CO2Read": null,
        "O2Read": null,
        "FanRead": null,
        "TempSensor1Read": 30.299,
        "TempSensor2Read": 31.164,
        "TempSensor3Read": 31.007
      },
      "setpoints": {
        "TempSet": 29.6,
        "HumSet": 58.6,
        "CO2Set": null,
        "O2Set": null,
        "FanSet": null
      }
    },
    {
      "timestamp": "2025-10-31T07:35:04.499006",
      "mode": "Timer",
      "readings": {
        "Temp1Read": 29.579,
        "HumRead": 58.578,
        "CO2Read": null,
        "O2Read": null,
        "FanRead": null,
        "TempSensor1Read": 30.297,
        "TempSensor2Read": 31.161,
        "TempSensor3Read": 31.005
      },
      "setpoints": {
        "TempSet": 29.6,
        "HumSet": 58.6,
        "CO2Set": null,
        "O2Set": null,
        "FanSet": null
      }
    },
    {
      "timestamp": "2025-10-31T07:36:16.098821",
      "mode": "Timer",
      "readings": {
        "Temp1Read": 29.571,
        "HumRead": 58.518,
        "CO2Read": null,
        "O2Read": null,
        "FanRead": null,
        "TempSensor1Read": 30.296,
        "TempSensor2Read": 31.158,
        "TempSensor3Read": 31.002
      },
      "setpoints": {
        "TempSet": 29.6,
        "HumSet": 58.6,
        "CO2Set": null,
        "O2Set": null,
        "FanSet": null
      }
    },
    {
      "timestamp": "2025-10-31T07:37:30.126485",
      "mode": "Timer",
      "readings": {
        "Temp1Read": 29.571,
        "HumRead": 58.387,
        "CO2Read": null,
        "O2Read": null,
        "FanRead": null,
        "TempSensor1Read": 30.294,
        "TempSensor2Read": 31.155,
        "TempSensor3Read": 31.001
      },
      "setpoints": {
        "TempSet": 30.4,
        "HumSet": 60.8,
        "CO2Set": null,
        "O2Set": null,
        "FanSet": null
      }
    },
    {
      "timestamp": "2025-10-31T07:39:01.301925",
      "mode": "Timer",
      "readings": {
        "Temp1Read": 29.599,
        "HumRead": 59.236,
        "CO2Read": null,
        "O2Read": null,
        "FanRead": null,
        "TempSensor1Read": 30.293,
        "TempSensor2Read": 31.152,
        "TempSensor3Read": 31.0
      },
      "setpoints": {
        "TempSet": 30.4,
        "HumSet": 60.8,
        "CO2Set": null,
        "O2Set": null,
        "FanSet": null
      }
    },
    {
      "timestamp": "2025-10-31T07:40:13.662881",
      "mode": "Timer",
      "readings": {
        "Temp1Read": 29.638,
        "HumRead": 61.067,
        "CO2Read": null,
        "O2Read": null,
        "FanRead": null,
        "TempSensor1Read": 30.291,
        "TempSensor2Read": 31.149,
        "TempSensor3Read": 31.001
      },
      "setpoints": {
        "TempSet": 30.4,
        "HumSet": 60.5,
        "CO2Set": null,
        "O2Set": null,
        "FanSet": null
      }
    },
    {
      "timestamp": "2025-10-31T07:42:03.330074",
      "mode": "Timer",
      "readings": {
        "Temp1Read": 29.657,
        "HumRead": 60.858,
        "CO2Read": null,
        "O2Read": null,
        "FanRead": null,
        "TempSensor1Read": 30.291,
        "TempSensor2Read": 31.147,
        "TempSensor3Read": 31.0
      },
      "setpoints": {
        "TempSet": 30.4,
        "HumSet": 58.3,
        "CO2Set": null,
        "O2Set": null,
        "FanSet": null
      }
    },
    {
      "timestamp": "2025-10-31T07:43:16.038547",
      "mode": "Timer",
      "readings": {
        "Temp1Read": 29.674,
        "HumRead": 60.374,
        "CO2Read": null,
        "O2Read": null,
        "FanRead": null,
        "TempSensor1Read": 30.291,
        "TempSensor2Read": 31.148,
        "TempSensor3Read": 31.002
      },
      "setpoints": {
        "TempSet": 30.3,
        "HumSet": 58.5,
        "CO2Set": null,
        "O2Set": null,
        "FanSet": null
      }
    },
    {
      "timestamp": "2025-10-31T07:44:47.925724",
      "mode": "Timer",
      "readings": {
        "Temp1Read": 29.704,
        "HumRead": 59.901,
        "CO2Read": null,
        "O2Read": null,
        "FanRead": null,
        "TempSensor1Read": 30.295,
        "TempSensor2Read": 31.151,
        "TempSensor3Read": 31.005
      },
      "setpoints": {
        "TempSet": 30.3,
        "HumSet": 59.0,
        "CO2Set": null,
        "O2Set": null,
        "FanSet": null
      }
    },
    {
      "timestamp": "2025-10-31T07:46:00.410334",
      "mode": "Timer",
      "readings": {
        "Temp1Read": 29.709,
        "HumRead": 59.501,
        "CO2Read": null,
        "O2Read": null,
        "FanRead": null,
        "TempSensor1Read": 30.3,
        "TempSensor2Read": 31.154,
        "TempSensor3Read": 31.01
      },
      "setpoints": {
        "TempSet": 30.3,
        "HumSet": 60.0,
        "CO2Set": null,
        "O2Set": null,
        "FanSet": null
      }
    },
    {
      "timestamp": "2025-10-31T07:47:13.319974",
      "mode": "Timer",
      "readings": {
        "Temp1Read": 29.745,
        "HumRead": 60.641,
        "CO2Read": null,
        "O2Read": null,
        "FanRead": null,
        "TempSensor1Read": 30.304,
        "TempSensor2Read": 31.16,
        "TempSensor3Read": 31.017
      },
      "setpoints": {
        "TempSet": 30.3,
        "HumSet": 60.4,
        "CO2Set": null,
        "O2Set": null,
        "FanSet": null
      }
    },
    {
      "timestamp": "2025-10-31T07:48:44.282359",
      "mode": "Timer",
      "readings": {
        "Temp1Read": 29.785,
        "HumRead": 60.606,
        "CO2Read": null,
        "O2Read": null,
        "FanRead": null,
        "TempSensor1Read": 30.312,
        "TempSensor2Read": 31.167,
        "TempSensor3Read": 31.024
      },
      "setpoints": {
        "TempSet": 30.3,
        "HumSet": 58.8,
        "CO2Set": null,
        "O2Set": null,
        "FanSet": null
      }
    },
    {
      "timestamp": "2025-10-31T07:50:15.537428",
      "mode": "Timer",
      "readings": {
        "Temp1Read": 29.811,
        "HumRead": 60.226,
        "CO2Read": null,
        "O2Read": null,
        "FanRead": null,
        "TempSensor1Read": 30.322,
        "TempSensor2Read": 31.176,
        "TempSensor3Read": 31.034
      },
      "setpoints": {
        "TempSet": 28.2,
        "HumSet": 58.9,
        "CO2Set": null,
        "O2Set": null,
        "FanSet": null
      }
    },
    {
      "timestamp": "2025-10-31T07:51:29.835021",
      "mode": "Timer",
      "readings": {
        "Temp1Read": 29.839,
        "HumRead": 59.684,
        "CO2Read": null,
        "O2Read": null,
        "FanRead": null,
        "TempSensor1Read": 30.331,
        "TempSensor2Read": 31.186,
        "TempSensor3Read": 31.044
      },
      "setpoints": {
        "TempSet": 28.2,
        "HumSet": 59.2,
        "CO2Set": null,
        "O2Set": null,
        "FanSet": null
      }
    },
    {
      "timestamp": "2025-10-31T07:53:31.147687",
      "mode": "Timer",
      "readings": {
        "Temp1Read": 29.82,
        "HumRead": 59.577,
        "CO2Read": null,
        "O2Read": null,
        "FanRead": null,
        "TempSensor1Read": 30.344,
        "TempSensor2Read": 31.2,
        "TempSensor3Read": 31.06
      },
      "setpoints": {
        "TempSet": 28.2,
        "HumSet": 59.2,
        "CO2Set": null,
        "O2Set": null,
        "FanSet": null
      }
    },
    {
      "timestamp": "2025-10-31T07:54:44.052771",
      "mode": "Timer",
      "readings": {
        "Temp1Read": 29.804,
        "HumRead": 59.547,
        "CO2Read": null,
        "O2Read": null,
        "FanRead": null,
        "TempSensor1Read": 30.357,
        "TempSensor2Read": 31.214,
        "TempSensor3Read": 31.072
      },
      "setpoints": {
        "TempSet": 28.2,
        "HumSet": 60.4,
        "CO2Set": null,
        "O2Set": null,
        "FanSet": null
      }
    },
    {
      "timestamp": "2025-10-31T07:55:56.337041",
      "mode": "Timer",
      "readings": {
        "Temp1Read": 29.787,
        "HumRead": 60.629,
        "CO2Read": null,
        "O2Read": null,
        "FanRead": null,
        "TempSensor1Read": 30.372,
        "TempSensor2Read": 31.227,
        "TempSensor3Read": 31.085
      },
      "setpoints": {
        "TempSet": 28.2,
        "HumSet": 60.4,
        "CO2Set": null,
        "O2Set": null,
        "FanSet": null
      }
    },
    {
      "timestamp": "2025-10-31T07:57:08.308748",
      "mode": "Timer",
      "readings": {
        "Temp1Read": 29.751,
        "HumRead": 60.986,
        "CO2Read": null,
        "O2Read": null,
        "FanRead": null,
        "TempSensor1Read": 30.382,
        "TempSensor2Read": 31.239,
        "TempSensor3Read": 31.092
      },
      "setpoints": {
        "TempSet": 28.2,
        "HumSet": 58.8,
        "CO2Set": null,
        "O2Set": null,
        "FanSet": null
      }
    },
    {
      "timestamp": "2025-10-31T07:58:20.959006",
      "mode": "Timer",
      "readings": {
        "Temp1Read": 29.726,
        "HumRead": 60.906,
        "CO2Read": null,
        "O2Read": null,
        "FanRead": null,
        "TempSensor1Read": 30.392,
        "TempSensor2Read": 31.251,
        "TempSensor3Read": 31.103
      },
      "setpoints": {
        "TempSet": 28.1,
        "HumSet": 58.4,
        "CO2Set": null,
        "O2Set": null,
        "FanSet": null
      }
    },
    {
      "timestamp": "2025-10-31T07:59:52.906154",
      "mode": "Timer",
      "readings": {
        "Temp1Read": 29.706,
        "HumRead": 60.484,
        "CO2Read": null,
        "O2Read": null,
        "FanRead": null,
        "TempSensor1Read": 30.4,
        "TempSensor2Read": 31.262,
        "TempSensor3Read": 31.112
      },
      "setpoints": {
        "TempSet": 28.1,
        "HumSet": 58.5,
        "CO2Set": null,
        "O2Set": null,
        "FanSet": null
      }
    },
    {
      "timestamp": "2025-10-31T08:01:07.275188",
      "mode": "Timer",
      "readings": {
        "Temp1Read": 29.657,
        "HumRead": 60.218,
        "CO2Read": null,
        "O2Read": null,
        "FanRead": null,
        "TempSensor1Read": 30.408,
        "TempSensor2Read": 31.271,
        "TempSensor3Read": 31.12
      },
      "setpoints": {
        "TempSet": 28.1,
        "HumSet": 58.9,
        "CO2Set": null,
        "O2Set": null,
        "FanSet": null
      }
    },
    {
      "timestamp": "2025-10-31T08:02:20.047083",
      "mode": "Timer",
      "readings": {
        "Temp1Read": 29.654,
        "HumRead": 59.842,
        "CO2Read": null,
        "O2Read": null,
        "FanRead": null,
        "TempSensor1Read": 30.413,
        "TempSensor2Read": 31.279,
        "TempSensor3Read": 31.12
      },
      "setpoints": {
        "TempSet": 28.1,
        "HumSet": 59.2,
        "CO2Set": null,
        "O2Set": null,
        "FanSet": null
      }
    },
    {
      "timestamp": "2025-10-31T08:03:50.889906",
      "mode": "Timer",
      "readings": {
        "Temp1Read": 29.611,
        "HumRead": 59.482,
        "CO2Read": null,
        "O2Read": null,
        "FanRead": null,
        "TempSensor1Read": 30.416,
        "TempSensor2Read": 31.285,
        "TempSensor3Read": 31.123
      },
      "setpoints": {
        "TempSet": 28.1,
        "HumSet": 60.1,
        "CO2Set": null,
        "O2Set": null,
        "FanSet": null
      }
    },
    {
      "timestamp": "2025-10-31T08:05:04.579222",
      "mode": "Timer",
      "readings": {
        "Temp1Read": 29.593,
        "HumRead": 60.333,
        "CO2Read": null,
        "O2Read": null,
        "FanRead": null,
        "TempSensor1Read": 30.415,
        "TempSensor2Read": 31.288,
        "TempSensor3Read": 31.119
      },
      "setpoints": {
        "TempSet": 28.1,
        "HumSet": 60.4,
        "CO2Set": null,
        "O2Set": null,
        "FanSet": null
      }
    },
    {
      "timestamp": "2025-10-31T08:06:16.905861",
      "mode": "Timer",
      "readings": {
        "Temp1Read": 29.577,
        "HumRead": 60.843,
        "CO2Read": null,
        "O2Read": null,
        "FanRead": null,
        "TempSensor1Read": 30.414,
        "TempSensor2Read": 31.288,
        "TempSensor3Read": 31.114
      },
      "setpoints": {
        "TempSet": 28.1,
        "HumSet": 59.1,
        "CO2Set": null,
        "O2Set": null,
        "FanSet": null
      }
    },
    {
      "timestamp": "2025-10-31T08:07:29.513206",
      "mode": "Timer",
      "readings": {
        "Temp1Read": 29.552,
        "HumRead": 60.635,
        "CO2Read": null,
        "O2Read": null,
        "FanRead": null,
        "TempSensor1Read": 30.409,
        "TempSensor2Read": 31.288,
        "TempSensor3Read": 31.107
      },
      "setpoints": {
        "TempSet": 28.1,
        "HumSet": 58.6,
        "CO2Set": null,
        "O2Set": null,
        "FanSet": null
      }
    },
    {
      "timestamp": "2025-10-31T08:09:00.705609",
      "mode": "Timer",
      "readings": {
        "Temp1Read": 29.507,
        "HumRead": 60.355,
        "CO2Read": null,
        "O2Read": null,
        "FanRead": null,
        "TempSensor1Read": 30.402,
        "TempSensor2Read": 31.284,
        "TempSensor3Read": 31.098
      },
      "setpoints": {
        "TempSet": 28.1,
        "HumSet": 58.8,
        "CO2Set": null,
        "O2Set": null,
        "FanSet": null
      }
    },
    {
      "timestamp": "2025-10-31T08:10:12.872192",
      "mode": "Timer",
      "readings": {
        "Temp1Read": 29.488,
        "HumRead": 60.214,
        "CO2Read": null,
        "O2Read": null,
        "FanRead": null,
        "TempSensor1Read": 30.393,
        "TempSensor2Read": 31.277,
        "TempSensor3Read": 31.086
      },
      "setpoints": {
        "TempSet": 28.1,
        "HumSet": 59.0,
        "CO2Set": null,
        "O2Set": null,
        "FanSet": null
      }
    },
    {
      "timestamp": "2025-10-31T08:11:26.585897",
      "mode": "Timer",
      "readings": {
        "Temp1Read": 29.468,
        "HumRead": 59.881,
        "CO2Read": null,
        "O2Read": null,
        "FanRead": null,
        "TempSensor1Read": 30.383,
        "TempSensor2Read": 31.269,
        "TempSensor3Read": 31.075
      },
      "setpoints": {
        "TempSet": 28.1,
        "HumSet": 59.2,
        "CO2Set": null,
        "O2Set": null,
        "FanSet": null
      }
    },
    {
      "timestamp": "2025-10-31T08:12:57.586529",
      "mode": "Timer",
      "readings": {
        "Temp1Read": 29.444,
        "HumRead": 59.359,
        "CO2Read": null,
        "O2Read": null,
        "FanRead": null,
        "TempSensor1Read": 30.371,
        "TempSensor2Read": 31.258,
        "TempSensor3Read": 31.06
      },
      "setpoints": {
        "TempSet": 28.1,
        "HumSet": 60.0,
        "CO2Set": null,
        "O2Set": null,
        "FanSet": null
      }
    },
    {
      "timestamp": "2025-10-31T08:14:11.572300",
      "mode": "Timer",
      "readings": {
        "Temp1Read": 29.413,
        "HumRead": 60.507,
        "CO2Read": null,
        "O2Read": null,
        "FanRead": null,
        "TempSensor1Read": 30.358,
        "TempSensor2Read": 31.245,
        "TempSensor3Read": 31.045
      },
      "setpoints": {
        "TempSet": 28.1,
        "HumSet": 60.5,
        "CO2Set": null,
        "O2Set": null,
        "FanSet": null
      }
    },
    {
      "timestamp": "2025-10-31T08:15:24.033642",
      "mode": "Timer",
      "readings": {
        "Temp1Read": 29.398,
        "HumRead": 60.979,
        "CO2Read": null,
        "O2Read": null,
        "FanRead": null,
        "TempSensor1Read": 30.343,
        "TempSensor2Read": 31.231,
        "TempSensor3Read": 31.03
      },
      "setpoints": {
        "TempSet": 28.1,
        "HumSet": 58.9,
        "CO2Set": null,
        "O2Set": null,
        "FanSet": null
      }
    },
    {
      "timestamp": "2025-10-31T08:16:56.433256",
      "mode": "Timer",
      "readings": {
        "Temp1Read": 29.37,
        "HumRead": 60.835,
        "CO2Read": null,
        "O2Read": null,
        "FanRead": null,
        "TempSensor1Read": 30.328,
        "TempSensor2Read": 31.215,
        "TempSensor3Read": 30.823
      },
      "setpoints": {
        "TempSet": 28.2,
        "HumSet": 58.4,
        "CO2Set": null,
        "O2Set": null,
        "FanSet": null
      }
    },
    {
      "timestamp": "2025-10-31T08:18:09.531892",
      "mode": "Timer",
      "readings": {
        "Temp1Read": 29.345,
        "HumRead": 60.562,
        "CO2Read": null,
        "O2Read": null,
        "FanRead": null,
        "TempSensor1Read": 30.314,
        "TempSensor2Read": 31.199,
        "TempSensor3Read": 30.846
      },
      "setpoints": {
        "TempSet": 28.1,
        "HumSet": 58.6,
        "CO2Set": null,
        "O2Set": null,
        "FanSet": null
      }
    },
    {
      "timestamp": "2025-10-31T08:19:22.012897",
      "mode": "Timer",
      "readings": {
        "Temp1Read": 29.323,
        "HumRead": 60.327,
        "CO2Read": null,
        "O2Read": null,
        "FanRead": null,
        "TempSensor1Read": 30.297,
        "TempSensor2Read": 31.183,
        "TempSensor3Read": 30.859
      },
      "setpoints": {
        "TempSet": 28.2,
        "HumSet": 58.8,
        "CO2Set": null,
        "O2Set": null,
        "FanSet": null
      }
    },
    {
      "timestamp": "2025-10-31T08:20:52.400678",
      "mode": "Timer",
      "readings": {
        "Temp1Read": 29.309,
        "HumRead": 59.994,
        "CO2Read": null,
        "O2Read": null,
        "FanRead": null,
        "TempSensor1Read": 30.278,
        "TempSensor2Read": 31.165,
        "TempSensor3Read": 30.863
      },
      "setpoints": {
        "TempSet": 28.2,
        "HumSet": 59.1,
        "CO2Set": null,
        "O2Set": null,
        "FanSet": null
      }
    },
    {
      "timestamp": "2025-10-31T08:22:04.974684",
      "mode": "Timer",
      "readings": {
        "Temp1Read": 29.294,
        "HumRead": 59.598,
        "CO2Read": null,
        "O2Read": null,
        "FanRead": null,
        "TempSensor1Read": 30.257,
        "TempSensor2Read": 31.146,
        "TempSensor3Read": 30.864
      },
      "setpoints": {
        "TempSet": 28.2,
        "HumSet": 59.8,
        "CO2Set": null,
        "O2Set": null,
        "FanSet": null
      }
    },
    {
      "timestamp": "2025-10-31T08:23:17.385202",
      "mode": "Timer",
      "readings": {
        "Temp1Read": 29.277,
        "HumRead": 59.844,
        "CO2Read": null,
        "O2Read": null,
        "FanRead": null,
        "TempSensor1Read": 30.239,
        "TempSensor2Read": 31.125,
        "TempSensor3Read": 30.858
      },
      "setpoints": {
        "TempSet": 28.2,
        "HumSet": 60.4,
        "CO2Set": null,
        "O2Set": null,
        "FanSet": null
      }
    },
    {
      "timestamp": "2025-10-31T08:24:31.192859",
      "mode": "Timer",
      "readings": {
        "Temp1Read": 29.242,
        "HumRead": 61.02,
        "CO2Read": null,
        "O2Read": null,
        "FanRead": null,
        "TempSensor1Read": 30.221,
        "TempSensor2Read": 31.105,
        "TempSensor3Read": 30.848
      },
      "setpoints": {
        "TempSet": 28.3,
        "HumSet": 60.3,
        "CO2Set": null,
        "O2Set": null,
        "FanSet": null
      }
    },
    {
      "timestamp": "2025-10-31T08:26:01.973489",
      "mode": "Timer",
      "readings": {
        "Temp1Read": 29.206,
        "HumRead": 60.899,
        "CO2Read": null,
        "O2Read": null,
        "FanRead": null,
        "TempSensor1Read": 30.201,
        "TempSensor2Read": 31.085,
        "TempSensor3Read": 30.833
      },
      "setpoints": {
        "TempSet": 28.3,
        "HumSet": 58.4,
        "CO2Set": null,
        "O2Set": null,
        "FanSet": null
      }
    },
    {
      "timestamp": "2025-10-31T08:27:14.682647",
      "mode": "Timer",
      "readings": {
        "Temp1Read": 29.176,
        "HumRead": 60.591,
        "CO2Read": null,
        "O2Read": null,
        "FanRead": null,
        "TempSensor1Read": 30.18,
        "TempSensor2Read": 31.065,
        "TempSensor3Read": 30.819
      },
      "setpoints": {
        "TempSet": 28.3,
        "HumSet": 58.5,
        "CO2Set": null,
        "O2Set": null,
        "FanSet": null
      }
    },
    {
      "timestamp": "2025-10-31T08:28:28.362728",
      "mode": "Timer",
      "readings": {
        "Temp1Read": 29.164,
        "HumRead": 60.384,
        "CO2Read": null,
        "O2Read": null,
        "FanRead": null,
        "TempSensor1Read": 30.16,
        "TempSensor2Read": 31.044,
        "TempSensor3Read": 30.802
      },
      "setpoints": {
        "TempSet": 28.4,
        "HumSet": 58.8,
        "CO2Set": null,
        "O2Set": null,
        "FanSet": null
      }
    },
    {
      "timestamp": "2025-10-31T08:29:59.786105",
      "mode": "Timer",
      "readings": {
        "Temp1Read": 29.148,
        "HumRead": 60.086,
        "CO2Read": null,
        "O2Read": null,
        "FanRead": null,
        "TempSensor1Read": 30.138,
        "TempSensor2Read": 31.023,
        "TempSensor3Read": 30.784
      },
      "setpoints": {
        "TempSet": 28.3,
        "HumSet": 59.0,
        "CO2Set": null,
        "O2Set": null,
        "FanSet": null
      }
    },
    {
      "timestamp": "2025-10-31T08:31:13.482863",
      "mode": "Timer",
      "readings": {
        "Temp1Read": 29.127,
        "HumRead": 59.711,
        "CO2Read": null,
        "O2Read": null,
        "FanRead": null,
        "TempSensor1Read": 30.115,
        "TempSensor2Read": 31.001,
        "TempSensor3Read": 30.765
      },
      "setpoints": {
        "TempSet": 28.4,
        "HumSet": 59.3,
        "CO2Set": null,
        "O2Set": null,
        "FanSet": null
      }
    },
    {
      "timestamp": "2025-10-31T08:32:26.870122",
      "mode": "Timer",
      "readings": {
        "Temp1Read": 29.096,
        "HumRead": 59.803,
        "CO2Read": null,
        "O2Read": null,
        "FanRead": null,
        "TempSensor1Read": 30.09,
        "TempSensor2Read": 30.98,
        "TempSensor3Read": 30.742
      },
      "setpoints": {
        "TempSet": 28.4,
        "HumSet": 60.3,
        "CO2Set": null,
        "O2Set": null,
        "FanSet": null
      }
    },
    {
      "timestamp": "2025-10-31T08:33:58.415768",
      "mode": "Timer",
      "readings": {
        "Temp1Read": 29.086,
        "HumRead": 60.741,
        "CO2Read": null,
        "O2Read": null,
        "FanRead": null,
        "TempSensor1Read": 30.065,
        "TempSensor2Read": 30.958,
        "TempSensor3Read": 30.721
      },
      "setpoints": {
        "TempSet": 28.4,
        "HumSet": 60.3,
        "CO2Set": null,
        "O2Set": null,
        "FanSet": null
      }
    },
    {
      "timestamp": "2025-10-31T08:35:11.014785",
      "mode": "Timer",
      "readings": {
        "Temp1Read": 29.064,
        "HumRead": 60.621,
        "CO2Read": null,
        "O2Read": null,
        "FanRead": null,
        "TempSensor1Read": 30.042,
        "TempSensor2Read": 30.936,
        "TempSensor3Read": 30.696
      },
      "setpoints": {
        "TempSet": 28.5,
        "HumSet": 58.7,
        "CO2Set": null,
        "O2Set": null,
        "FanSet": null
      }
    },
    {
      "timestamp": "2025-10-31T08:36:23.706227",
      "mode": "Timer",
      "readings": {
        "Temp1Read": 29.045,
        "HumRead": 60.446,
        "CO2Read": null,
        "O2Read": null,
        "FanRead": null,
        "TempSensor1Read": 30.02,
        "TempSensor2Read": 30.914,
        "TempSensor3Read": 30.675
      },
      "setpoints": {
        "TempSet": 28.5,
        "HumSet": 58.8,
        "CO2Set": null,
        "O2Set": null,
        "FanSet": null
      }
    },
    {
      "timestamp": "2025-10-31T08:37:55.934173",
      "mode": "Timer",
      "readings": {
        "Temp1Read": 29.001,
        "HumRead": 60.137,
        "CO2Read": null,
        "O2Read": null,
        "FanRead": null,
        "TempSensor1Read": 29.995,
        "TempSensor2Read": 30.889,
        "TempSensor3Read": 30.656
      },
      "setpoints": {
        "TempSet": 28.5,
        "HumSet": 59.0,
        "CO2Set": null,
        "O2Set": null,
        "FanSet": null
      }
    },
    {
      "timestamp": "2025-10-31T08:39:09.248022",
      "mode": "Timer",
      "readings": {
        "Temp1Read": 28.975,
        "HumRead": 59.897,
        "CO2Read": null,
        "O2Read": null,
        "FanRead": null,
        "TempSensor1Read": 29.971,
        "TempSensor2Read": 30.866,
        "TempSensor3Read": 30.633
      },
      "setpoints": {
        "TempSet": 28.6,
        "HumSet": 59.3,
        "CO2Set": null,
        "O2Set": null,
        "FanSet": null
      }
    },
    {
      "timestamp": "2025-10-31T08:40:21.889602",
      "mode": "Timer",
      "readings": {
        "Temp1Read": 28.951,
        "HumRead": 59.841,
        "CO2Read": null,
        "O2Read": null,
        "FanRead": null,
        "TempSensor1Read": 29.95,
        "TempSensor2Read": 30.843,
        "TempSensor3Read": 30.609
      },
      "setpoints": {
        "TempSet": 28.6,
        "HumSet": 60.0,
        "CO2Set": null,
        "O2Set": null,
        "FanSet": null
      }
    },
    {
      "timestamp": "2025-10-31T08:41:52.954239",
      "mode": "Timer",
      "readings": {
        "Temp1Read": 28.932,
        "HumRead": 60.56,
        "CO2Read": null,
        "O2Read": null,
        "FanRead": null,
        "TempSensor1Read": 29.818,
        "TempSensor2Read": 30.819,
        "TempSensor3Read": 30.591
      },
      "setpoints": {
        "TempSet": 28.6,
        "HumSet": 60.3,
        "CO2Set": null,
        "O2Set": null,
        "FanSet": null
      }
    },
    {
      "timestamp": "2025-10-31T08:43:04.775482",
      "mode": "Timer",
      "readings": {
        "Temp1Read": 28.911,
        "HumRead": 60.648,
        "CO2Read": null,
        "O2Read": null,
        "FanRead": null,
        "TempSensor1Read": 29.821,
        "TempSensor2Read": 30.794,
        "TempSensor3Read": 30.568
      },
      "setpoints": {
        "TempSet": 28.6,
        "HumSet": 58.8,
        "CO2Set": null,
        "O2Set": null,
        "FanSet": null
      }
    },
    {
      "timestamp": "2025-10-31T08:44:18.439657",
      "mode": "Timer",
      "readings": {
        "Temp1Read": 28.881,
        "HumRead": 60.402,
        "CO2Read": null,
        "O2Read": null,
        "FanRead": null,
        "TempSensor1Read": 29.818,
        "TempSensor2Read": 30.771,
        "TempSensor3Read": 30.542
      },
      "setpoints": {
        "TempSet": 28.7,
        "HumSet": 58.8,
        "CO2Set": null,
        "O2Set": null,
        "FanSet": null
      }
    },
    {
      "timestamp": "2025-10-31T08:45:31.098753",
      "mode": "Timer",
      "readings": {
        "Temp1Read": 28.856,
        "HumRead": 60.357,
        "CO2Read": null,
        "O2Read": null,
        "FanRead": null,
        "TempSensor1Read": 29.808,
        "TempSensor2Read": 30.747,
        "TempSensor3Read": 30.517
      },
      "setpoints": {
        "TempSet": 28.7,
        "HumSet": 58.8,
        "CO2Set": null,
        "O2Set": null,
        "FanSet": null
      }
    },
    {
      "timestamp": "2025-10-31T08:47:02.867345",
      "mode": "Timer",
      "readings": {
        "Temp1Read": 28.815,
        "HumRead": 59.929,
        "CO2Read": null,
        "O2Read": null,
        "FanRead": null,
        "TempSensor1Read": 29.796,
        "TempSensor2Read": 30.722,
        "TempSensor3Read": 30.494
      },
      "setpoints": {
        "TempSet": 28.7,
        "HumSet": 59.1,
        "CO2Set": null,
        "O2Set": null,
        "FanSet": null
      }
    },
    {
      "timestamp": "2025-10-31T08:48:16.386167",
      "mode": "Timer",
      "readings": {
        "Temp1Read": 28.785,
        "HumRead": 59.815,
        "CO2Read": null,
        "O2Read": null,
        "FanRead": null,
        "TempSensor1Read": 29.78,
        "TempSensor2Read": 30.697,
        "TempSensor3Read": 30.47
      },
      "setpoints": {
        "TempSet": 28.8,
        "HumSet": 59.9,
        "CO2Set": null,
        "O2Set": null,
        "FanSet": null
      }
    },
    {
      "timestamp": "2025-10-31T08:49:28.312315",
      "mode": "Timer",
      "readings": {
        "Temp1Read": 28.76,
        "HumRead": 60.382,
        "CO2Read": null,
        "O2Read": null,
        "FanRead": null,
        "TempSensor1Read": 29.764,
        "TempSensor2Read": 30.672,
        "TempSensor3Read": 30.447
      },
      "setpoints": {
        "TempSet": 28.8,
        "HumSet": 60.2,
        "CO2Set": null,
        "O2Set": null,
        "FanSet": null
      }
    },
    {
      "timestamp": "2025-10-31T08:51:17.979753",
      "mode": "Timer",
      "readings": {
        "Temp1Read": 28.727,
        "HumRead": 60.647,
        "CO2Read": null,
        "O2Read": null,
        "FanRead": null,
        "TempSensor1Read": 29.741,
        "TempSensor2Read": 30.645,
        "TempSensor3Read": 30.314
      },
      "setpoints": {
        "TempSet": 28.8,
        "HumSet": 59.0,
        "CO2Set": null,
        "O2Set": null,
        "FanSet": null
      }
    },
    {
      "timestamp": "2025-10-31T08:52:31.224077",
      "mode": "Timer",
      "readings": {
        "Temp1Read": 28.718,
        "HumRead": 60.339,
        "CO2Read": null,
        "O2Read": null,
        "FanRead": null,
        "TempSensor1Read": 29.718,
        "TempSensor2Read": 30.619,
        "TempSensor3Read": 30.311
      },
      "setpoints": {
        "TempSet": 28.9,
        "HumSet": 58.8,
        "CO2Set": null,
        "O2Set": null,
        "FanSet": null
      }
    },
    {
      "timestamp": "2025-10-31T08:53:43.853198",
      "mode": "Timer",
      "readings": {
        "Temp1Read": 28.687,
        "HumRead": 60.261,
        "CO2Read": null,
        "O2Read": null,
        "FanRead": null,
        "TempSensor1Read": 29.698,
        "TempSensor2Read": 30.594,
        "TempSensor3Read": 30.306
      },
      "setpoints": {
        "TempSet": 28.9,
        "HumSet": 59.1,
        "CO2Set": null,
        "O2Set": null,
        "FanSet": null
      }
    }
  ]
}